{"DFpJSQ5y12OHpV2HAAAH": {"clientName": "172.16.213.39", "data": {"collection": "", "database": "Quality", "files": ["RA15 device list per posizionamento automatico.xlsx"], "galleria": "", "script": "Posizionamento dispositivi negli impianti", "subCollection": "", "userId": "DFpJSQ5y12OHpV2HAAAH"}, "id": "DFpJSQ5y12OHpV2HAAAH", "links": [], "message": [{"message": "RA15 device list per posizionamento automatico.xlsx"}, {"message": "Cercando..."}, {"message": "1|7: RA15-SINOTTICO-GENERALE"}, {"message": "2|7: RA15-KM-0-4"}, {"message": "3|7: RA15-KM-4-8"}, {"message": "4|7: RA15-KM-8-12"}, {"message": "inserimento:\t1:42 > RA15_KM_8_070_DIR_SR - (x: 10, y: 10) - [show: True] in -> RA15-KM-8-12"}, {"message": "inserimento:\t2:42 > RA15_KM_8_085_DIR_ME - (x: 55, y: 10) - [show: True] in -> RA15-KM-8-12"}, {"message": "inserimento:\t3:42 > RA15_KM_8_255_DIR_ME - (x: 100, y: 10) - [show: True] in -> RA15-KM-8-12"}, {"message": "inserimento:\t4:42 > RA15_KM_8_280_DIR_SR - (x: 145, y: 10) - [show: True] in -> RA15-KM-8-12"}, {"message": "inserimento:\t5:42 > RA15_KM_8_530_DIR_ME - (x: 190, y: 10) - [show: True] in -> RA15-KM-8-12"}, {"message": "inserimento:\t6:42 > RA15_KM_8_530_DIR_SR - (x: 235, y: 10) - [show: True] in -> RA15-KM-8-12"}, {"message": "inserimento:\t7:42 > RA15_KM_8_620_DIR_SR - (x: 280, y: 10) - [show: True] in -> RA15-KM-8-12"}, {"message": "inserimento:\t8:42 > RA15_KM_8_625_DIR_ME - (x: 325, y: 10) - [show: True] in -> RA15-KM-8-12"}, {"message": "inserimento:\t9:42 > RA15_KM_8_740_DIR_ME - (x: 370, y: 10) - [show: True] in -> RA15-KM-8-12"}, {"message": "inserimento:\t10:42 > RA15_KM_8_760_DIR_SR - (x: 415, y: 10) - [show: True] in -> RA15-KM-8-12"}, {"message": "inserimento:\t11:42 > RA15_KM_8_980_DIR_ME - (x: 460, y: 10) - [show: True] in -> RA15-KM-8-12"}, {"message": "inserimento:\t12:42 > RA15_KM_8_980_DIR_SR - (x: 505, y: 10) - [show: True] in -> RA15-KM-8-12"}, {"message": "inserimento:\t13:42 > RA15_KM_9_160_DIR_ME - (x: 550, y: 10) - [show: True] in -> RA15-KM-8-12"}, {"message": "inserimento:\t14:42 > RA15_KM_9_160_DIR_SR - (x: 595, y: 10) - [show: True] in -> RA15-KM-8-12"}, {"message": "inserimento:\t15:42 > RA15_KM_9_400_DIR_ME - (x: 640, y: 10) - [show: True] in -> RA15-KM-8-12"}, {"message": "inserimento:\t16:42 > RA15_KM_9_400_DIR_SR - (x: 685, y: 10) - [show: True] in -> RA15-KM-8-12"}, {"message": "inserimento:\t17:42 > RA15_KM_9_615_DIR_ME - (x: 730, y: 10) - [show: True] in -> RA15-KM-8-12"}, {"message": "inserimento:\t18:42 > RA15_KM_9_615_DIR_SR - (x: 775, y: 10) - [show: True] in -> RA15-KM-8-12"}, {"message": "inserimento:\t19:42 > RA15_KM_9_820_DIR_SR - (x: 820, y: 10) - [show: True] in -> RA15-KM-8-12"}, {"message": "inserimento:\t20:42 > RA15_KM_9_850_DIR_ME - (x: 865, y: 10) - [show: True] in -> RA15-KM-8-12"}, {"message": "inserimento:\t21:42 > RA15_KM_10_050_DIR_SR - (x: 910, y: 10) - [show: True] in -> RA15-KM-8-12"}, {"message": "inserimento:\t22:42 > RA15_KM_10_100_DIR_ME - (x: 955, y: 10) - [show: True] in -> RA15-KM-8-12"}, {"message": "inserimento:\t23:42 > RA15_KM_10_300_DIR_ME - (x: 1000, y: 10) - [show: True] in -> RA15-KM-8-12"}, {"message": "inserimento:\t24:42 > RA15_KM_10_300_DIR_SR - (x: 1045, y: 10) - [show: True] in -> RA15-KM-8-12"}, {"message": "inserimento:\t25:42 > RA15_KM_10_530_DIR_ME - (x: 1090, y: 10) - [show: True] in -> RA15-KM-8-12"}, {"message": "inserimento:\t26:42 > RA15_KM_10_550_DIR_SR - (x: 1135, y: 10) - [show: True] in -> RA15-KM-8-12"}, {"message": "inserimento:\t27:42 > RA15_KM_10_700_DIR_ME - (x: 1180, y: 10) - [show: True] in -> RA15-KM-8-12"}, {"message": "inserimento:\t28:42 > RA15_KM_10_700_DIR_SR - (x: 1225, y: 10) - [show: True] in -> RA15-KM-8-12"}, {"message": "inserimento:\t29:42 > RA15_KM_10_790_DIR_ME - (x: 1270, y: 10) - [show: True] in -> RA15-KM-8-12"}, {"message": "inserimento:\t30:42 > RA15_KM_10_790_DIR_SR - (x: 1315, y: 10) - [show: True] in -> RA15-KM-8-12"}, {"message": "inserimento:\t31:42 > RA15_KM_11_000_DIR_ME - (x: 1360, y: 10) - [show: True] in -> RA15-KM-8-12"}, {"message": "inserimento:\t32:42 > RA15_KM_11_000_DIR_SR - (x: 1405, y: 10) - [show: True] in -> RA15-KM-8-12"}, {"message": "inserimento:\t33:42 > RA15_KM_11_180_DIR_ME - (x: 1450, y: 10) - [show: True] in -> RA15-KM-8-12"}, {"message": "inserimento:\t34:42 > RA15_KM_11_190_DIR_SR - (x: 1495, y: 10) - [show: True] in -> RA15-KM-8-12"}, {"message": "inserimento:\t35:42 > RA15_KM_11_250_DIR_ME - (x: 1540, y: 10) - [show: True] in -> RA15-KM-8-12"}, {"message": "inserimento:\t36:42 > RA15_KM_11_250_DIR_SR - (x: 1585, y: 10) - [show: True] in -> RA15-KM-8-12"}, {"message": "inserimento:\t37:42 > RA15_KM_11_500_DIR_ME - (x: 1630, y: 10) - [show: True] in -> RA15-KM-8-12"}, {"message": "inserimento:\t38:42 > RA15_KM_11_500_DIR_SR - (x: 1675, y: 10) - [show: True] in -> RA15-KM-8-12"}, {"message": "inserimento:\t39:42 > RA15_KM_11_750_DIR_ME - (x: 1720, y: 10) - [show: True] in -> RA15-KM-8-12"}, {"message": "inserimento:\t40:42 > RA15_KM_11_750_DIR_SR - (x: 1765, y: 10) - [show: True] in -> RA15-KM-8-12"}, {"message": "inserimento:\t41:42 > RA15_KM_12_000_DIR_ME - (x: 1810, y: 10) - [show: True] in -> RA15-KM-8-12"}, {"message": "inserimento:\t42:42 > RA15_KM_12_000_DIR_SR - (x: 1855, y: 10) - [show: True] in -> RA15-KM-8-12"}, {"message": "5|7: RA15-KM-12-16"}, {"message": "6|7: RA15-KM-16-20"}, {"message": "7|7: RA15-KM-20-24"}, {"message": "Finito"}, {"message": "Tempo elaborazione: 0:04 minuti"}], "progress": 100.5, "task": "Posizionamento dispositivi negli impianti (OLD).py", "timestamp": "2025-10-13_11.36.17"}, "Eccg5u5eow_N_8V0AAAL": {"clientName": "172.16.215.59", "data": {"collection": "", "database": "Quality", "files": ["CONDO device list per posizionamento automatico.xlsx"], "galleria": "", "script": "Posizionamento dispositivi negli impianti", "subCollection": "", "userId": "Eccg5u5eow_N_8V0AAAL"}, "id": "Eccg5u5eow_N_8V0AAAL", "links": [], "message": [{"message": "CONDO device list per posizionamento automatico.xlsx"}, {"message": "Cercando..."}, {"message": "1|17: CONDO-SINOTTICO-GENERALE"}, {"message": "inserimento:\t1:588 > CONDO-ABILITAZIONE-DA-RMT - (x: 10, y: 10) - [show: True] in -> CONDO-SINOTTICO-GENERALE"}, {"message": "inserimento:\t2:588 > CONDO-ALLARME-INCENDIO - (x: 55, y: 10) - [show: True] in -> CONDO-SINOTTICO-GENERALE"}, {"message": "inserimento:\t3:588 > CONDO-AN1-A - (x: 100, y: 10) - [show: True] in -> CONDO-SINOTTICO-GENERALE"}, {"message": "inserimento:\t4:588 > CONDO-AN1-B - (x: 145, y: 10) - [show: True] in -> CONDO-SINOTTICO-GENERALE"}, {"message": "inserimento:\t5:588 > CONDO-CE-QGBT-INT-QG1 - (x: 190, y: 10) - [show: False] in -> CONDO-SINOTTICO-GENERALE"}, {"message": "inserimento:\t6:588 > CONDO-CE-QIS-INT-Q1 - (x: 190, y: 10) - [show: False] in -> CONDO-SINOTTICO-GENERALE"}, {"message": "inserimento:\t7:588 > CONDO-CE-QIS-INT-Q2 - (x: 190, y: 10) - [show: False] in -> CONDO-SINOTTICO-GENERALE"}, {"message": "inserimento:\t8:588 > CONDO-CE-QIS-INT-Q32 - (x: 190, y: 10) - [show: False] in -> CONDO-SINOTTICO-GENERALE"}, {"message": "inserimento:\t9:588 > CONDO-CE-QIS-INT-Q33 - (x: 190, y: 10) - [show: False] in -> CONDO-SINOTTICO-GENERALE"}, {"message": "inserimento:\t10:588 > CONDO-CE-QIS-INT-Q34 - (x: 190, y: 10) - [show: False] in -> CONDO-SINOTTICO-GENERALE"}, {"message": "inserimento:\t11:588 > CONDO-CE-QIS-INT-Q35 - (x: 190, y: 10) - [show: False] in -> CONDO-SINOTTICO-GENERALE"}, {"message": "inserimento:\t12:588 > CONDO-CE-QIS-INT-Q36 - (x: 190, y: 10) - [show: False] in -> CONDO-SINOTTICO-GENERALE"}, {"message": "inserimento:\t13:588 > CONDO-CE-QIS-INT-Q37 - (x: 190, y: 10) - [show: False] in -> CONDO-SINOTTICO-GENERALE"}, {"message": "inserimento:\t14:588 > CONDO-CE-QIS-INT-Q38 - (x: 190, y: 10) - [show: False] in -> CONDO-SINOTTICO-GENERALE"}, {"message": "inserimento:\t15:588 > CONDO-CE-QIS-INT-Q39 - (x: 190, y: 10) - [show: False] in -> CONDO-SINOTTICO-GENERALE"}, {"message": "inserimento:\t16:588 > CONDO-CE-QIS-INT-Q40 - (x: 190, y: 10) - [show: False] in -> CONDO-SINOTTICO-GENERALE"}, {"message": "inserimento:\t17:588 > CONDO-CE-QIS-INT-Q41 - (x: 190, y: 10) - [show: False] in -> CONDO-SINOTTICO-GENERALE"}, {"message": "inserimento:\t18:588 > CONDO-CENTRALINA-FIBROLASER - (x: 190, y: 10) - [show: True] in -> CONDO-SINOTTICO-GENERALE"}, {"message": "inserimento:\t19:588 > CONDO-CENTRALINA-RILEVAZIONE-INCENDIO-US1 - (x: 235, y: 10) - [show: True] in -> CONDO-SINOTTICO-GENERALE"}, {"message": "inserimento:\t20:588 > CONDO-CENTRALINA-RILEVAZIONE-INCENDIO-US2 - (x: 280, y: 10) - [show: True] in -> CONDO-SINOTTICO-GENERALE"}, {"message": "inserimento:\t21:588 > CONDO-CO1-A - (x: 325, y: 10) - [show: True] in -> CONDO-SINOTTICO-GENERALE"}, {"message": "inserimento:\t22:588 > CONDO-CO1-B - (x: 370, y: 10) - [show: True] in -> CONDO-SINOTTICO-GENERALE"}, {"message": "inserimento:\t23:588 > CONDO-CO2-A - (x: 415, y: 10) - [show: True] in -> CONDO-SINOTTICO-GENERALE"}, {"message": "inserimento:\t24:588 > CONDO-CO2-B - (x: 460, y: 10) - [show: True] in -> CONDO-SINOTTICO-GENERALE"}, {"message": "inserimento:\t25:588 > CONDO-COLONNINA-SOS-1A - (x: 505, y: 10) - [show: True] in -> CONDO-SINOTTICO-GENERALE"}, {"message": "inserimento:\t26:588 > CONDO-COLONNINA-SOS-1B - (x: 550, y: 10) - [show: True] in -> CONDO-SINOTTICO-GENERALE"}, {"message": "inserimento:\t27:588 > CONDO-COLONNINA-SOS-2A - (x: 595, y: 10) - [show: True] in -> CONDO-SINOTTICO-GENERALE"}, {"message": "inserimento:\t28:588 > CONDO-COLONNINA-SOS-2B - (x: 640, y: 10) - [show: True] in -> CONDO-SINOTTICO-GENERALE"}, {"message": "inserimento:\t29:588 > CONDO-COLONNINA-SOS-3A - (x: 685, y: 10) - [show: True] in -> CONDO-SINOTTICO-GENERALE"}, {"message": "inserimento:\t30:588 > CONDO-COLONNINA-SOS-3B - (x: 730, y: 10) - [show: True] in -> CONDO-SINOTTICO-GENERALE"}, {"message": "inserimento:\t31:588 > CONDO-COLONNINA-SOS-4A - (x: 775, y: 10) - [show: True] in -> CONDO-SINOTTICO-GENERALE"}, {"message": "inserimento:\t32:588 > CONDO-COLONNINA-SOS-4B - (x: 820, y: 10) - [show: True] in -> CONDO-SINOTTICO-GENERALE"}, {"message": "inserimento:\t33:588 > CONDO-COLONNINA-SOS-5A - (x: 865, y: 10) - [show: True] in -> CONDO-SINOTTICO-GENERALE"}, {"message": "inserimento:\t34:588 > CONDO-COLONNINA-SOS-5B - (x: 910, y: 10) - [show: True] in -> CONDO-SINOTTICO-GENERALE"}, {"message": "inserimento:\t35:588 > CONDO-COLONNINA-SOS-6A - (x: 955, y: 10) - [show: True] in -> CONDO-SINOTTICO-GENERALE"}, {"message": "inserimento:\t36:588 > CONDO-COLONNINA-SOS-6B - (x: 1000, y: 10) - [show: True] in -> CONDO-SINOTTICO-GENERALE"}, {"message": "inserimento:\t37:588 > CONDO-COLONNINA-SOS-7A - (x: 1045, y: 10) - [show: True] in -> CONDO-SINOTTICO-GENERALE"}, {"message": "inserimento:\t38:588 > CONDO-COLONNINA-SOS-7B - (x: 1090, y: 10) - [show: True] in -> CONDO-SINOTTICO-GENERALE"}, {"message": "inserimento:\t39:588 > CONDO-COLONNINA-SOS-8A - (x: 1135, y: 10) - [show: True] in -> CONDO-SINOTTICO-GENERALE"}, {"message": "inserimento:\t40:588 > CONDO-COLONNINA-SOS-8B - (x: 1180, y: 10) - [show: True] in -> CONDO-SINOTTICO-GENERALE"}, {"message": "inserimento:\t41:588 > CONDO-COLONNINA-SOS-9A - (x: 1225, y: 10) - [show: True] in -> CONDO-SINOTTICO-GENERALE"}, {"message": "inserimento:\t42:588 > CONDO-COLONNINA-SOS-9B - (x: 1270, y: 10) - [show: True] in -> CONDO-SINOTTICO-GENERALE"}, {"message": "inserimento:\t43:588 > CONDO-COLONNINA-SOS-10A - (x: 1315, y: 10) - [show: True] in -> CONDO-SINOTTICO-GENERALE"}, {"message": "inserimento:\t44:588 > CONDO-COLONNINA-SOS-10B - (x: 1360, y: 10) - [show: True] in -> CONDO-SINOTTICO-GENERALE"}, {"message": "inserimento:\t45:588 > CONDO-FRECCIA-CROCE-ESTERNO-MARCIA - (x: 1405, y: 10) - [show: True] in -> CONDO-SINOTTICO-GENERALE"}, {"message": "inserimento:\t46:588 > CONDO-FRECCIA-CROCE-ESTERNO-SORPASSO - (x: 1450, y: 10) - [show: True] in -> CONDO-SINOTTICO-GENERALE"}, {"message": "inserimento:\t47:588 > CONDO-FRECCIA-CROCE-PMV1A-MARCIA - (x: 1495, y: 10) - [show: True] in -> CONDO-SINOTTICO-GENERALE"}, {"message": "inserimento:\t48:588 > CONDO-FRECCIA-CROCE-PMV1A-SORPASSO - (x: 1540, y: 10) - [show: True] in -> CONDO-SINOTTICO-GENERALE"}, {"message": "inserimento:\t49:588 > CONDO-FRECCIA-CROCE-PMV1B-MARCIA - (x: 1585, y: 10) - [show: True] in -> CONDO-SINOTTICO-GENERALE"}, {"message": "inserimento:\t50:588 > CONDO-FRECCIA-CROCE-PMV1B-SORPASSO - (x: 1630, y: 10) - [show: True] in -> CONDO-SINOTTICO-GENERALE"}, {"message": "inserimento:\t51:588 > CONDO-FRECCIA-CROCE-PMV2A-MARCIA - (x: 1675, y: 10) - [show: True] in -> CONDO-SINOTTICO-GENERALE"}, {"message": "inserimento:\t52:588 > CONDO-FRECCIA-CROCE-PMV2A-SORPASSO - (x: 1720, y: 10) - [show: True] in -> CONDO-SINOTTICO-GENERALE"}, {"message": "inserimento:\t53:588 > CONDO-FRECCIA-CROCE-PMV2B-MARCIA - (x: 1765, y: 10) - [show: True] in -> CONDO-SINOTTICO-GENERALE"}, {"message": "inserimento:\t54:588 > CONDO-FRECCIA-CROCE-PMV2B-SORPASSO - (x: 1810, y: 10) - [show: True] in -> CONDO-SINOTTICO-GENERALE"}, {"message": "inserimento:\t55:588 > CONDO-FRECCIA-CROCE-PMV3A-MARCIA - (x: 1855, y: 10) - [show: True] in -> CONDO-SINOTTICO-GENERALE"}, {"message": "inserimento:\t56:588 > CONDO-FRECCIA-CROCE-PMV3A-SORPASSO - (x: 1900, y: 10) - [show: True] in -> CONDO-SINOTTICO-GENERALE"}, {"message": "inserimento:\t57:588 > CONDO-FRECCIA-CROCE-PMV3B-MARCIA - (x: 1945, y: 10) - [show: True] in -> CONDO-SINOTTICO-GENERALE"}, {"message": "inserimento:\t58:588 > CONDO-FRECCIA-CROCE-PMV3B-SORPASSO - (x: 90, y: 35) - [show: True] in -> CONDO-SINOTTICO-GENERALE"}, {"message": "inserimento:\t59:588 > CONDO-FRECCIA-CROCE-PMV4A-MARCIA - (x: 135, y: 35) - [show: True] in -> CONDO-SINOTTICO-GENERALE"}, {"message": "inserimento:\t60:588 > CONDO-FRECCIA-CROCE-PMV4A-SORPASSO - (x: 180, y: 35) - [show: True] in -> CONDO-SINOTTICO-GENERALE"}, {"message": "inserimento:\t61:588 > CONDO-FRECCIA-CROCE-PMV4B-MARCIA - (x: 225, y: 35) - [show: True] in -> CONDO-SINOTTICO-GENERALE"}, {"message": "inserimento:\t62:588 > CONDO-FRECCIA-CROCE-PMV4B-SORPASSO - (x: 270, y: 35) - [show: True] in -> CONDO-SINOTTICO-GENERALE"}, {"message": "inserimento:\t63:588 > CONDO-FRECCIA-CROCE-PMV5A-MARCIA - (x: 315, y: 35) - [show: True] in -> CONDO-SINOTTICO-GENERALE"}, {"message": "inserimento:\t64:588 > CONDO-FRECCIA-CROCE-PMV5A-SORPASSO - (x: 360, y: 35) - [show: True] in -> CONDO-SINOTTICO-GENERALE"}, {"message": "inserimento:\t65:588 > CONDO-FRECCIA-CROCE-PMV5B-MARCIA - (x: 405, y: 35) - [show: True] in -> CONDO-SINOTTICO-GENERALE"}, {"message": "inserimento:\t66:588 > CONDO-FRECCIA-CROCE-PMV5B-SORPASSO - (x: 450, y: 35) - [show: True] in -> CONDO-SINOTTICO-GENERALE"}, {"message": "inserimento:\t67:588 > CONDO-GRUPPO-ELETTROGENO - (x: 495, y: 35) - [show: True] in -> CONDO-SINOTTICO-GENERALE"}, {"message": "inserimento:\t68:588 > CONDO-LANTERNA-SEMAFORICA-MARCIA - (x: 540, y: 35) - [show: True] in -> CONDO-SINOTTICO-GENERALE"}, {"message": "inserimento:\t69:588 > CONDO-LANTERNA-SEMAFORICA-SORPASSO - (x: 585, y: 35) - [show: True] in -> CONDO-SINOTTICO-GENERALE"}, {"message": "inserimento:\t70:588 > CONDO-OP1-A - (x: 630, y: 35) - [show: True] in -> CONDO-SINOTTICO-GENERALE"}, {"message": "inserimento:\t71:588 > CONDO-OP1-B - (x: 675, y: 35) - [show: True] in -> CONDO-SINOTTICO-GENERALE"}, {"message": "inserimento:\t72:588 > CONDO-OP2-A - (x: 720, y: 35) - [show: True] in -> CONDO-SINOTTICO-GENERALE"}, {"message": "inserimento:\t73:588 > CONDO-OP2-B - (x: 765, y: 35) - [show: True] in -> CONDO-SINOTTICO-GENERALE"}, {"message": "inserimento:\t74:588 > CONDO-PLC-MASTER - (x: 810, y: 35) - [show: True] in -> CONDO-SINOTTICO-GENERALE"}, {"message": "inserimento:\t75:588 > CONDO-QVVF-A - (x: 855, y: 35) - [show: True] in -> CONDO-SINOTTICO-GENERALE"}, {"message": "inserimento:\t76:588 > CONDO-QVVF-B - (x: 900, y: 35) - [show: True] in -> CONDO-SINOTTICO-GENERALE"}, {"message": "inserimento:\t77:588 > CONDO-RESET-ALLARMI-TUNNEL-A - (x: 945, y: 35) - [show: True] in -> CONDO-SINOTTICO-GENERALE"}, {"message": "inserimento:\t78:588 > CONDO-RESET-ALLARMI-TUNNEL-B - (x: 990, y: 35) - [show: True] in -> CONDO-SINOTTICO-GENERALE"}, {"message": "inserimento:\t79:588 > CONDO-RILEVATORE-INCENDIO-ZONA-1-A - (x: 1035, y: 35) - [show: True] in -> CONDO-SINOTTICO-GENERALE"}, {"message": "inserimento:\t80:588 > CONDO-RILEVATORE-INCENDIO-ZONA-1-B - (x: 1080, y: 35) - [show: True] in -> CONDO-SINOTTICO-GENERALE"}, {"message": "inserimento:\t81:588 > CONDO-RILEVATORE-INCENDIO-ZONA-2-A - (x: 1125, y: 35) - [show: True] in -> CONDO-SINOTTICO-GENERALE"}, {"message": "inserimento:\t82:588 > CONDO-RILEVATORE-INCENDIO-ZONA-2-B - (x: 1170, y: 35) - [show: True] in -> CONDO-SINOTTICO-GENERALE"}, {"message": "inserimento:\t83:588 > CONDO-RILEVATORE-INCENDIO-ZONA-3-A - (x: 1215, y: 35) - [show: True] in -> CONDO-SINOTTICO-GENERALE"}, {"message": "inserimento:\t84:588 > CONDO-RILEVATORE-INCENDIO-ZONA-3-B - (x: 1260, y: 35) - [show: True] in -> CONDO-SINOTTICO-GENERALE"}, {"message": "inserimento:\t85:588 > CONDO-SCENARI-GALLERIA - (x: 1305, y: 35) - [show: True] in -> CONDO-SINOTTICO-GENERALE"}, {"message": "inserimento:\t86:588 > CONDO-UPS - (x: 1350, y: 35) - [show: True] in -> CONDO-SINOTTICO-GENERALE"}, {"message": "inserimento:\t87:588 > CONDO-VENTILATORE-V1A - (x: 1395, y: 35) - [show: True] in -> CONDO-SINOTTICO-GENERALE"}, {"message": "inserimento:\t88:588 > CONDO-VENTILATORE-V1B - (x: 1440, y: 35) - [show: True] in -> CONDO-SINOTTICO-GENERALE"}, {"message": "inserimento:\t89:588 > CONDO-VENTILATORE-V2A - (x: 1485, y: 35) - [show: True] in -> CONDO-SINOTTICO-GENERALE"}, {"message": "inserimento:\t90:588 > CONDO-VENTILATORE-V2B - (x: 1530, y: 35) - [show: True] in -> CONDO-SINOTTICO-GENERALE"}, {"message": "inserimento:\t91:588 > CONDO-VENTILATORE-V3A - (x: 1575, y: 35) - [show: True] in -> CONDO-SINOTTICO-GENERALE"}, {"message": "inserimento:\t92:588 > CONDO-VENTILATORE-V3B - (x: 1620, y: 35) - [show: True] in -> CONDO-SINOTTICO-GENERALE"}, {"message": "inserimento:\t93:588 > CONDO-VENTILATORE-V4A - (x: 1665, y: 35) - [show: True] in -> CONDO-SINOTTICO-GENERALE"}, {"message": "inserimento:\t94:588 > CONDO-VENTILATORE-V4B - (x: 1710, y: 35) - [show: True] in -> CONDO-SINOTTICO-GENERALE"}, {"message": "inserimento:\t95:588 > CONDO-VENTILATORE-V5A - (x: 1755, y: 35) - [show: True] in -> CONDO-SINOTTICO-GENERALE"}, {"message": "inserimento:\t96:588 > CONDO-VENTILATORE-V5B - (x: 1800, y: 35) - [show: True] in -> CONDO-SINOTTICO-GENERALE"}, {"message": "inserimento:\t97:588 > CONDO-VENTILATORE-V6A - (x: 1845, y: 35) - [show: True] in -> CONDO-SINOTTICO-GENERALE"}, {"message": "inserimento:\t98:588 > CONDO-VENTILATORE-V6B - (x: 1890, y: 35) - [show: True] in -> CONDO-SINOTTICO-GENERALE"}, {"message": "inserimento:\t99:588 > CONDO-VENTILATORE-V7A - (x: 1935, y: 35) - [show: True] in -> CONDO-SINOTTICO-GENERALE"}, {"message": "inserimento:\t100:588 > CONDO-VENTILATORE-V7B - (x: 90, y: 60) - [show: True] in -> CONDO-SINOTTICO-GENERALE"}, {"message": "inserimento:\t101:588 > PMV_SS694_Gall_Condo_Km_3_870_DIR_Gallipoli_Esterno - (x: 135, y: 60) - [show: True] in -> CONDO-SINOTTICO-GENERALE"}, {"message": "inserimento:\t102:588 > PMV_SS694_Gall_Condo_Km_5_018_DIR_BR - (x: 180, y: 60) - [show: True] in -> CONDO-SINOTTICO-GENERALE"}, {"message": "inserimento:\t103:588 > PMV_SS694_Gall_Condo_Km_5_140_DIR_BR_Esterno - (x: 225, y: 60) - [show: True] in -> CONDO-SINOTTICO-GENERALE"}, {"message": "inserimento:\t104:588 > SS694_Gall_Condo_Km_4_010_TVCC15_B - (x: 270, y: 60) - [show: True] in -> CONDO-SINOTTICO-GENERALE"}, {"message": "inserimento:\t105:588 > SS694_Gall_Condo_Km_4_025_DIR_Gallipoli - (x: 315, y: 60) - [show: True] in -> CONDO-SINOTTICO-GENERALE"}, {"message": "inserimento:\t106:588 > SS694_Gall_Condo_Km_4_029_DIR_BR - (x: 360, y: 60) - [show: True] in -> CONDO-SINOTTICO-GENERALE"}, {"message": "inserimento:\t107:588 > SS694_Gall_Condo_Km_4_044_TVCC15_A - (x: 405, y: 60) - [show: True] in -> CONDO-SINOTTICO-GENERALE"}, {"message": "inserimento:\t108:588 > SS694_Gall_Condo_Km_4_095_TVCC1_B - (x: 450, y: 60) - [show: True] in -> CONDO-SINOTTICO-GENERALE"}, {"message": "inserimento:\t109:588 > SS694_Gall_Condo_Km_4_124_TVCC14_A - (x: 495, y: 60) - [show: True] in -> CONDO-SINOTTICO-GENERALE"}, {"message": "inserimento:\t110:588 > SS694_Gall_Condo_Km_4_170_TVCC2_B - (x: 540, y: 60) - [show: True] in -> CONDO-SINOTTICO-GENERALE"}, {"message": "inserimento:\t111:588 > SS694_Gall_Condo_Km_4_194_TVCC13_A - (x: 585, y: 60) - [show: True] in -> CONDO-SINOTTICO-GENERALE"}, {"message": "inserimento:\t112:588 > SS694_Gall_Condo_Km_4_219_DIR_BR - (x: 630, y: 60) - [show: True] in -> CONDO-SINOTTICO-GENERALE"}, {"message": "inserimento:\t113:588 > SS694_Gall_Condo_Km_4_245_TVCC3_B - (x: 675, y: 60) - [show: True] in -> CONDO-SINOTTICO-GENERALE"}, {"message": "inserimento:\t114:588 > SS694_Gall_Condo_Km_4_274_TVCC12_A - (x: 720, y: 60) - [show: True] in -> CONDO-SINOTTICO-GENERALE"}, {"message": "inserimento:\t115:588 > SS694_Gall_Condo_Km_4_320_DIR_Gallipoli - (x: 765, y: 60) - [show: True] in -> CONDO-SINOTTICO-GENERALE"}, {"message": "inserimento:\t116:588 > SS694_Gall_Condo_Km_4_320_TVCC4_B - (x: 810, y: 60) - [show: True] in -> CONDO-SINOTTICO-GENERALE"}, {"message": "inserimento:\t117:588 > SS694_Gall_Condo_Km_4_344_TVCC11_A - (x: 855, y: 60) - [show: True] in -> CONDO-SINOTTICO-GENERALE"}, {"message": "inserimento:\t118:588 > SS694_Gall_Condo_Km_4_395_TVCC5_B - (x: 900, y: 60) - [show: True] in -> CONDO-SINOTTICO-GENERALE"}, {"message": "inserimento:\t119:588 > SS694_Gall_Condo_Km_4_424_TVCC10_A - (x: 945, y: 60) - [show: True] in -> CONDO-SINOTTICO-GENERALE"}, {"message": "inserimento:\t120:588 > SS694_Gall_Condo_Km_4_470_TVCC6_B - (x: 990, y: 60) - [show: True] in -> CONDO-SINOTTICO-GENERALE"}, {"message": "inserimento:\t121:588 > SS694_Gall_Condo_Km_4_494_TVCC9_A - (x: 1035, y: 60) - [show: True] in -> CONDO-SINOTTICO-GENERALE"}, {"message": "inserimento:\t122:588 > SS694_Gall_Condo_Km_4_545_TVCC7_B - (x: 1080, y: 60) - [show: True] in -> CONDO-SINOTTICO-GENERALE"}, {"message": "inserimento:\t123:588 > SS694_Gall_Condo_Km_4_574_TVCC8_A - (x: 1125, y: 60) - [show: True] in -> CONDO-SINOTTICO-GENERALE"}, {"message": "inserimento:\t124:588 > SS694_Gall_Condo_Km_4_584_TVCC18_AUE - (x: 1170, y: 60) - [show: True] in -> CONDO-SINOTTICO-GENERALE"}, {"message": "inserimento:\t125:588 > SS694_Gall_Condo_Km_4_591_TVCC17_AUE - (x: 1215, y: 60) - [show: True] in -> CONDO-SINOTTICO-GENERALE"}, {"message": "inserimento:\t126:588 > SS694_Gall_Condo_Km_4_597_TVCC16_AUE - (x: 1260, y: 60) - [show: True] in -> CONDO-SINOTTICO-GENERALE"}, {"message": "inserimento:\t127:588 > SS694_Gall_Condo_Km_4_607_TVCC8_B - (x: 1305, y: 60) - [show: True] in -> CONDO-SINOTTICO-GENERALE"}, {"message": "inserimento:\t128:588 > SS694_Gall_Condo_Km_4_610_TVCC9_B - (x: 1350, y: 60) - [show: True] in -> CONDO-SINOTTICO-GENERALE"}, {"message": "inserimento:\t129:588 > SS694_Gall_Condo_Km_4_620_DIR_Gallipoli - (x: 1395, y: 60) - [show: True] in -> CONDO-SINOTTICO-GENERALE"}, {"message": "inserimento:\t130:588 > SS694_Gall_Condo_Km_4_624_TVCC7_A - (x: 1440, y: 60) - [show: True] in -> CONDO-SINOTTICO-GENERALE"}, {"message": "inserimento:\t131:588 > SS694_Gall_Condo_Km_4_644_TVCC6_A - (x: 1485, y: 60) - [show: True] in -> CONDO-SINOTTICO-GENERALE"}, {"message": "inserimento:\t132:588 > SS694_Gall_Condo_Km_4_663_TVCC16_BUE - (x: 1530, y: 60) - [show: True] in -> CONDO-SINOTTICO-GENERALE"}, {"message": "inserimento:\t133:588 > SS694_Gall_Condo_Km_4_669_TVCC17_BUE - (x: 1575, y: 60) - [show: True] in -> CONDO-SINOTTICO-GENERALE"}, {"message": "inserimento:\t134:588 > SS694_Gall_Condo_Km_4_675_TVCC18_BUE - (x: 1620, y: 60) - [show: True] in -> CONDO-SINOTTICO-GENERALE"}, {"message": "inserimento:\t135:588 > SS694_Gall_Condo_Km_4_695_TVCC10_B - (x: 1665, y: 60) - [show: True] in -> CONDO-SINOTTICO-GENERALE"}, {"message": "inserimento:\t136:588 > SS694_Gall_Condo_Km_4_719_DIR_BR - (x: 1710, y: 60) - [show: True] in -> CONDO-SINOTTICO-GENERALE"}, {"message": "inserimento:\t137:588 > SS694_Gall_Condo_Km_4_724_TVCC5_A - (x: 1755, y: 60) - [show: True] in -> CONDO-SINOTTICO-GENERALE"}, {"message": "inserimento:\t138:588 > SS694_Gall_Condo_Km_4_770_TVCC11_B - (x: 1800, y: 60) - [show: True] in -> CONDO-SINOTTICO-GENERALE"}, {"message": "inserimento:\t139:588 > SS694_Gall_Condo_Km_4_794_TVCC4_A - (x: 1845, y: 60) - [show: True] in -> CONDO-SINOTTICO-GENERALE"}, {"message": "inserimento:\t140:588 > SS694_Gall_Condo_Km_4_845_TVCC12_B - (x: 1890, y: 60) - [show: True] in -> CONDO-SINOTTICO-GENERALE"}, {"message": "inserimento:\t141:588 > SS694_Gall_Condo_Km_4_874_TVCC3_A - (x: 1935, y: 60) - [show: True] in -> CONDO-SINOTTICO-GENERALE"}, {"message": "inserimento:\t142:588 > SS694_Gall_Condo_Km_4_920_DIR_Gallipoli - (x: 90, y: 85) - [show: True] in -> CONDO-SINOTTICO-GENERALE"}, {"message": "inserimento:\t143:588 > SS694_Gall_Condo_Km_4_920_TVCC13_B - (x: 135, y: 85) - [show: True] in -> CONDO-SINOTTICO-GENERALE"}, {"message": "inserimento:\t144:588 > SS694_Gall_Condo_Km_4_944_TVCC2_A - (x: 180, y: 85) - [show: True] in -> CONDO-SINOTTICO-GENERALE"}, {"message": "inserimento:\t145:588 > SS694_Gall_Condo_Km_4_995_TVCC14_B - (x: 225, y: 85) - [show: True] in -> CONDO-SINOTTICO-GENERALE"}, {"message": "inserimento:\t146:588 > SS694_Gall_Condo_Km_5_009_TVCC1_A - (x: 270, y: 85) - [show: True] in -> CONDO-SINOTTICO-GENERALE"}, {"message": "2|17: CONDO-IMPIANTO-ELETTRICO"}, {"message": "inserimento:\t1:588 > CONDO-GRUPPO-ELETTROGENO - (x: 10, y: 10) - [show: True] in -> CONDO-IMPIANTO-ELETTRICO"}, {"message": "inserimento:\t2:588 > CONDO-TRAFO - (x: 55, y: 10) - [show: True] in -> CONDO-IMPIANTO-ELETTRICO"}, {"message": "inserimento:\t3:588 > CONDO-UPS - (x: 100, y: 10) - [show: True] in -> CONDO-IMPIANTO-ELETTRICO"}, {"message": "3|17: CONDO-IMPIANTO-ILLUMINAZIONE"}, {"message": "inserimento:\t1:588 > CONDO-CE-QIS-INT-Q1 - (x: 10, y: 10) - [show: False] in -> CONDO-IMPIANTO-ILLUMINAZIONE"}, {"message": "inserimento:\t2:588 > CONDO-CE-QIS-INT-Q2 - (x: 10, y: 10) - [show: False] in -> CONDO-IMPIANTO-ILLUMINAZIONE"}, {"message": "inserimento:\t3:588 > CONDO-CE-QIS-INT-Q3 - (x: 10, y: 10) - [show: False] in -> CONDO-IMPIANTO-ILLUMINAZIONE"}, {"message": "inserimento:\t4:588 > CONDO-CE-QIS-INT-Q4 - (x: 10, y: 10) - [show: False] in -> CONDO-IMPIANTO-ILLUMINAZIONE"}, {"message": "inserimento:\t5:588 > CONDO-CE-QIS-INT-Q5 - (x: 10, y: 10) - [show: False] in -> CONDO-IMPIANTO-ILLUMINAZIONE"}, {"message": "inserimento:\t6:588 > CONDO-CE-QIS-INT-Q6 - (x: 10, y: 10) - [show: False] in -> CONDO-IMPIANTO-ILLUMINAZIONE"}, {"message": "inserimento:\t7:588 > CONDO-CE-QIS-INT-Q32 - (x: 10, y: 10) - [show: False] in -> CONDO-IMPIANTO-ILLUMINAZIONE"}, {"message": "inserimento:\t8:588 > CONDO-CE-QIS-INT-Q33 - (x: 10, y: 10) - [show: False] in -> CONDO-IMPIANTO-ILLUMINAZIONE"}, {"message": "inserimento:\t9:588 > CONDO-CE-QIS-INT-Q34 - (x: 10, y: 10) - [show: False] in -> CONDO-IMPIANTO-ILLUMINAZIONE"}, {"message": "inserimento:\t10:588 > CONDO-CE-QIS-INT-Q35 - (x: 10, y: 10) - [show: False] in -> CONDO-IMPIANTO-ILLUMINAZIONE"}, {"message": "inserimento:\t11:588 > CONDO-CE-QIS-INT-Q36 - (x: 10, y: 10) - [show: False] in -> CONDO-IMPIANTO-ILLUMINAZIONE"}, {"message": "inserimento:\t12:588 > CONDO-CE-QIS-INT-Q37 - (x: 10, y: 10) - [show: False] in -> CONDO-IMPIANTO-ILLUMINAZIONE"}, {"message": "inserimento:\t13:588 > CONDO-CE-QIS-INT-Q38 - (x: 10, y: 10) - [show: False] in -> CONDO-IMPIANTO-ILLUMINAZIONE"}, {"message": "inserimento:\t14:588 > CONDO-CE-QIS-INT-Q39 - (x: 10, y: 10) - [show: False] in -> CONDO-IMPIANTO-ILLUMINAZIONE"}, {"message": "inserimento:\t15:588 > CONDO-CE-QIS-INT-Q40 - (x: 10, y: 10) - [show: False] in -> CONDO-IMPIANTO-ILLUMINAZIONE"}, {"message": "inserimento:\t16:588 > CONDO-CE-QIS-INT-Q41 - (x: 10, y: 10) - [show: False] in -> CONDO-IMPIANTO-ILLUMINAZIONE"}, {"message": "inserimento:\t17:588 > CONDO-ILLUMINAZIONE-RINFORZO-A-NORD - (x: 10, y: 10) - [show: True] in -> CONDO-IMPIANTO-ILLUMINAZIONE"}, {"message": "inserimento:\t18:588 > CONDO-ILLUMINAZIONE-RINFORZO-B-SUD - (x: 55, y: 10) - [show: True] in -> CONDO-IMPIANTO-ILLUMINAZIONE"}, {"message": "4|17: CONDO-IMPIANTO-RETE-DATI"}, {"message": "inserimento:\t1:588 > CONDO-GATEWAY-VOIP - (x: 10, y: 10) - [show: True] in -> CONDO-IMPIANTO-RETE-DATI"}, {"message": "inserimento:\t2:588 > CONDO-PLC-MASTER - (x: 55, y: 10) - [show: True] in -> CONDO-IMPIANTO-RETE-DATI"}, {"message": "inserimento:\t3:588 > CONDO-RIO-SOS-1A - (x: 100, y: 10) - [show: True] in -> CONDO-IMPIANTO-RETE-DATI"}, {"message": "inserimento:\t4:588 > CONDO-RIO-SOS-1B - (x: 145, y: 10) - [show: True] in -> CONDO-IMPIANTO-RETE-DATI"}, {"message": "inserimento:\t5:588 > CONDO-RIO-SOS-2A - (x: 190, y: 10) - [show: True] in -> CONDO-IMPIANTO-RETE-DATI"}, {"message": "inserimento:\t6:588 > CONDO-RIO-SOS-2B - (x: 235, y: 10) - [show: True] in -> CONDO-IMPIANTO-RETE-DATI"}, {"message": "inserimento:\t7:588 > CONDO-RIO-SOS-3A - (x: 280, y: 10) - [show: True] in -> CONDO-IMPIANTO-RETE-DATI"}, {"message": "inserimento:\t8:588 > CONDO-RIO-SOS-3B - (x: 325, y: 10) - [show: True] in -> CONDO-IMPIANTO-RETE-DATI"}, {"message": "inserimento:\t9:588 > CONDO-RIO-SOS-4A - (x: 370, y: 10) - [show: True] in -> CONDO-IMPIANTO-RETE-DATI"}, {"message": "inserimento:\t10:588 > CONDO-RIO-SOS-4B - (x: 415, y: 10) - [show: True] in -> CONDO-IMPIANTO-RETE-DATI"}, {"message": "inserimento:\t11:588 > CONDO-RIO-SOS-5A - (x: 460, y: 10) - [show: True] in -> CONDO-IMPIANTO-RETE-DATI"}, {"message": "inserimento:\t12:588 > CONDO-RIO-SOS-5B - (x: 505, y: 10) - [show: True] in -> CONDO-IMPIANTO-RETE-DATI"}, {"message": "inserimento:\t13:588 > CONDO-RIO-SOS-6A - (x: 550, y: 10) - [show: True] in -> CONDO-IMPIANTO-RETE-DATI"}, {"message": "inserimento:\t14:588 > CONDO-RIO-SOS-6B - (x: 595, y: 10) - [show: True] in -> CONDO-IMPIANTO-RETE-DATI"}, {"message": "inserimento:\t15:588 > CONDO-RIO-SOS-7A - (x: 640, y: 10) - [show: True] in -> CONDO-IMPIANTO-RETE-DATI"}, {"message": "inserimento:\t16:588 > CONDO-RIO-SOS-7B - (x: 685, y: 10) - [show: True] in -> CONDO-IMPIANTO-RETE-DATI"}, {"message": "inserimento:\t17:588 > CONDO-RIO-SOS-8A - (x: 730, y: 10) - [show: True] in -> CONDO-IMPIANTO-RETE-DATI"}, {"message": "inserimento:\t18:588 > CONDO-RIO-SOS-8B - (x: 775, y: 10) - [show: True] in -> CONDO-IMPIANTO-RETE-DATI"}, {"message": "inserimento:\t19:588 > CONDO-RIO-SOS-9A - (x: 820, y: 10) - [show: True] in -> CONDO-IMPIANTO-RETE-DATI"}, {"message": "inserimento:\t20:588 > CONDO-RIO-SOS-9B - (x: 865, y: 10) - [show: True] in -> CONDO-IMPIANTO-RETE-DATI"}, {"message": "inserimento:\t21:588 > CONDO-RIO-SOS-10B - (x: 910, y: 10) - [show: True] in -> CONDO-IMPIANTO-RETE-DATI"}, {"message": "inserimento:\t22:588 > CONDO-SCADA-SERVER - (x: 955, y: 10) - [show: True] in -> CONDO-IMPIANTO-RETE-DATI"}, {"message": "inserimento:\t23:588 > CONDO-SWITCH-DATI-SW-CE - (x: 1000, y: 10) - [show: True] in -> CONDO-IMPIANTO-RETE-DATI"}, {"message": "inserimento:\t24:588 > CONDO-SWITCH-DATI-SW-SOS1-A - (x: 1045, y: 10) - [show: True] in -> CONDO-IMPIANTO-RETE-DATI"}, {"message": "inserimento:\t25:588 > CONDO-SWITCH-DATI-SW-SOS1-B - (x: 1090, y: 10) - [show: True] in -> CONDO-IMPIANTO-RETE-DATI"}, {"message": "inserimento:\t26:588 > CONDO-SWITCH-DATI-SW-SOS2-A - (x: 1135, y: 10) - [show: True] in -> CONDO-IMPIANTO-RETE-DATI"}, {"message": "inserimento:\t27:588 > CONDO-SWITCH-DATI-SW-SOS2-B - (x: 1180, y: 10) - [show: True] in -> CONDO-IMPIANTO-RETE-DATI"}, {"message": "inserimento:\t28:588 > CONDO-SWITCH-DATI-SW-SOS3-A - (x: 1225, y: 10) - [show: True] in -> CONDO-IMPIANTO-RETE-DATI"}, {"message": "inserimento:\t29:588 > CONDO-SWITCH-DATI-SW-SOS3-B - (x: 1270, y: 10) - [show: True] in -> CONDO-IMPIANTO-RETE-DATI"}, {"message": "inserimento:\t30:588 > CONDO-SWITCH-DATI-SW-SOS4-A - (x: 1315, y: 10) - [show: True] in -> CONDO-IMPIANTO-RETE-DATI"}, {"message": "inserimento:\t31:588 > CONDO-SWITCH-DATI-SW-SOS4-B - (x: 1360, y: 10) - [show: True] in -> CONDO-IMPIANTO-RETE-DATI"}, {"message": "inserimento:\t32:588 > CONDO-SWITCH-DATI-SW-SOS5-A - (x: 1405, y: 10) - [show: True] in -> CONDO-IMPIANTO-RETE-DATI"}, {"message": "inserimento:\t33:588 > CONDO-SWITCH-DATI-SW-SOS5-B - (x: 1450, y: 10) - [show: True] in -> CONDO-IMPIANTO-RETE-DATI"}, {"message": "inserimento:\t34:588 > CONDO-SWITCH-DATI-SW-SOS6-A - (x: 1495, y: 10) - [show: True] in -> CONDO-IMPIANTO-RETE-DATI"}, {"message": "inserimento:\t35:588 > CONDO-SWITCH-DATI-SW-SOS6-B - (x: 1540, y: 10) - [show: True] in -> CONDO-IMPIANTO-RETE-DATI"}, {"message": "inserimento:\t36:588 > CONDO-SWITCH-DATI-SW-SOS7-A - (x: 1585, y: 10) - [show: True] in -> CONDO-IMPIANTO-RETE-DATI"}, {"message": "inserimento:\t37:588 > CONDO-SWITCH-DATI-SW-SOS7-B - (x: 1630, y: 10) - [show: True] in -> CONDO-IMPIANTO-RETE-DATI"}, {"message": "inserimento:\t38:588 > CONDO-SWITCH-DATI-SW-SOS8-A - (x: 1675, y: 10) - [show: True] in -> CONDO-IMPIANTO-RETE-DATI"}, {"message": "inserimento:\t39:588 > CONDO-SWITCH-DATI-SW-SOS8-B - (x: 1720, y: 10) - [show: True] in -> CONDO-IMPIANTO-RETE-DATI"}, {"message": "inserimento:\t40:588 > CONDO-SWITCH-DATI-SW-SOS9-A - (x: 1765, y: 10) - [show: True] in -> CONDO-IMPIANTO-RETE-DATI"}, {"message": "inserimento:\t41:588 > CONDO-SWITCH-DATI-SW-SOS9-B - (x: 1810, y: 10) - [show: True] in -> CONDO-IMPIANTO-RETE-DATI"}, {"message": "inserimento:\t42:588 > CONDO-SWITCH-DATI-SW-SOS10-A - (x: 1855, y: 10) - [show: True] in -> CONDO-IMPIANTO-RETE-DATI"}, {"message": "inserimento:\t43:588 > CONDO-SWITCH-DATI-SW-SOS10-B - (x: 1900, y: 10) - [show: True] in -> CONDO-IMPIANTO-RETE-DATI"}, {"message": "inserimento:\t44:588 > CONDO-SWITCH-DATI-SW-SOS11-A - (x: 1945, y: 10) - [show: True] in -> CONDO-IMPIANTO-RETE-DATI"}, {"message": "inserimento:\t45:588 > CONDO-SWITCH-DATI-SW-SOS11-B - (x: 90, y: 35) - [show: True] in -> CONDO-IMPIANTO-RETE-DATI"}, {"message": "inserimento:\t46:588 > CONDO-VIDEO-SERVER - (x: 135, y: 35) - [show: True] in -> CONDO-IMPIANTO-RETE-DATI"}, {"message": "inserimento:\t47:588 > CONDO-VOIP-SOS-1A - (x: 180, y: 35) - [show: True] in -> CONDO-IMPIANTO-RETE-DATI"}, {"message": "inserimento:\t48:588 > CONDO-VOIP-SOS-1B - (x: 225, y: 35) - [show: True] in -> CONDO-IMPIANTO-RETE-DATI"}, {"message": "inserimento:\t49:588 > CONDO-VOIP-SOS-2A - (x: 270, y: 35) - [show: True] in -> CONDO-IMPIANTO-RETE-DATI"}, {"message": "inserimento:\t50:588 > CONDO-VOIP-SOS-2B - (x: 315, y: 35) - [show: True] in -> CONDO-IMPIANTO-RETE-DATI"}, {"message": "inserimento:\t51:588 > CONDO-VOIP-SOS-3A - (x: 360, y: 35) - [show: True] in -> CONDO-IMPIANTO-RETE-DATI"}, {"message": "inserimento:\t52:588 > CONDO-VOIP-SOS-3B - (x: 405, y: 35) - [show: True] in -> CONDO-IMPIANTO-RETE-DATI"}, {"message": "inserimento:\t53:588 > CONDO-VOIP-SOS-4A - (x: 450, y: 35) - [show: True] in -> CONDO-IMPIANTO-RETE-DATI"}, {"message": "inserimento:\t54:588 > CONDO-VOIP-SOS-4B - (x: 495, y: 35) - [show: True] in -> CONDO-IMPIANTO-RETE-DATI"}, {"message": "inserimento:\t55:588 > CONDO-VOIP-SOS-5A - (x: 540, y: 35) - [show: True] in -> CONDO-IMPIANTO-RETE-DATI"}, {"message": "inserimento:\t56:588 > CONDO-VOIP-SOS-5B - (x: 585, y: 35) - [show: True] in -> CONDO-IMPIANTO-RETE-DATI"}, {"message": "inserimento:\t57:588 > CONDO-VOIP-SOS-6A - (x: 630, y: 35) - [show: True] in -> CONDO-IMPIANTO-RETE-DATI"}, {"message": "inserimento:\t58:588 > CONDO-VOIP-SOS-6B - (x: 675, y: 35) - [show: True] in -> CONDO-IMPIANTO-RETE-DATI"}, {"message": "inserimento:\t59:588 > CONDO-VOIP-SOS-7A - (x: 720, y: 35) - [show: True] in -> CONDO-IMPIANTO-RETE-DATI"}, {"message": "inserimento:\t60:588 > CONDO-VOIP-SOS-7B - (x: 765, y: 35) - [show: True] in -> CONDO-IMPIANTO-RETE-DATI"}, {"message": "inserimento:\t61:588 > CONDO-VOIP-SOS-8A - (x: 810, y: 35) - [show: True] in -> CONDO-IMPIANTO-RETE-DATI"}, {"message": "inserimento:\t62:588 > CONDO-VOIP-SOS-8B - (x: 855, y: 35) - [show: True] in -> CONDO-IMPIANTO-RETE-DATI"}, {"message": "inserimento:\t63:588 > CONDO-VOIP-SOS-9A - (x: 900, y: 35) - [show: True] in -> CONDO-IMPIANTO-RETE-DATI"}, {"message": "inserimento:\t64:588 > CONDO-VOIP-SOS-9B - (x: 945, y: 35) - [show: True] in -> CONDO-IMPIANTO-RETE-DATI"}, {"message": "inserimento:\t65:588 > CONDO-VOIP-SOS-USCITA-A - (x: 990, y: 35) - [show: True] in -> CONDO-IMPIANTO-RETE-DATI"}, {"message": "inserimento:\t66:588 > CONDO-VOIP-SOS-USCITA-B - (x: 1035, y: 35) - [show: True] in -> CONDO-IMPIANTO-RETE-DATI"}, {"message": "5|17: CONDO-IMPIANTO-SOS"}, {"message": "inserimento:\t1:588 > CONDO-CENTRALE-SONORA - (x: 10, y: 10) - [show: True] in -> CONDO-IMPIANTO-SOS"}, {"message": "inserimento:\t2:588 > CONDO-COLONNINA-SOS-1A - (x: 55, y: 10) - [show: True] in -> CONDO-IMPIANTO-SOS"}, {"message": "inserimento:\t3:588 > CONDO-COLONNINA-SOS-1B - (x: 100, y: 10) - [show: True] in -> CONDO-IMPIANTO-SOS"}, {"message": "inserimento:\t4:588 > CONDO-COLONNINA-SOS-2A - (x: 145, y: 10) - [show: True] in -> CONDO-IMPIANTO-SOS"}, {"message": "inserimento:\t5:588 > CONDO-COLONNINA-SOS-2B - (x: 190, y: 10) - [show: True] in -> CONDO-IMPIANTO-SOS"}, {"message": "inserimento:\t6:588 > CONDO-COLONNINA-SOS-3A - (x: 235, y: 10) - [show: True] in -> CONDO-IMPIANTO-SOS"}, {"message": "inserimento:\t7:588 > CONDO-COLONNINA-SOS-3B - (x: 280, y: 10) - [show: True] in -> CONDO-IMPIANTO-SOS"}, {"message": "inserimento:\t8:588 > CONDO-COLONNINA-SOS-4A - (x: 325, y: 10) - [show: True] in -> CONDO-IMPIANTO-SOS"}, {"message": "inserimento:\t9:588 > CONDO-COLONNINA-SOS-4B - (x: 370, y: 10) - [show: True] in -> CONDO-IMPIANTO-SOS"}, {"message": "inserimento:\t10:588 > CONDO-COLONNINA-SOS-5A - (x: 415, y: 10) - [show: True] in -> CONDO-IMPIANTO-SOS"}, {"message": "inserimento:\t11:588 > CONDO-COLONNINA-SOS-5B - (x: 460, y: 10) - [show: True] in -> CONDO-IMPIANTO-SOS"}, {"message": "inserimento:\t12:588 > CONDO-COLONNINA-SOS-6A - (x: 505, y: 10) - [show: True] in -> CONDO-IMPIANTO-SOS"}, {"message": "inserimento:\t13:588 > CONDO-COLONNINA-SOS-6B - (x: 550, y: 10) - [show: True] in -> CONDO-IMPIANTO-SOS"}, {"message": "inserimento:\t14:588 > CONDO-COLONNINA-SOS-7A - (x: 595, y: 10) - [show: True] in -> CONDO-IMPIANTO-SOS"}, {"message": "inserimento:\t15:588 > CONDO-COLONNINA-SOS-7B - (x: 640, y: 10) - [show: True] in -> CONDO-IMPIANTO-SOS"}, {"message": "inserimento:\t16:588 > CONDO-COLONNINA-SOS-8A - (x: 685, y: 10) - [show: True] in -> CONDO-IMPIANTO-SOS"}, {"message": "inserimento:\t17:588 > CONDO-COLONNINA-SOS-8B - (x: 730, y: 10) - [show: True] in -> CONDO-IMPIANTO-SOS"}, {"message": "inserimento:\t18:588 > CONDO-COLONNINA-SOS-9A - (x: 775, y: 10) - [show: True] in -> CONDO-IMPIANTO-SOS"}, {"message": "inserimento:\t19:588 > CONDO-COLONNINA-SOS-9B - (x: 820, y: 10) - [show: True] in -> CONDO-IMPIANTO-SOS"}, {"message": "inserimento:\t20:588 > CONDO-COLONNINA-SOS-10A - (x: 865, y: 10) - [show: True] in -> CONDO-IMPIANTO-SOS"}, {"message": "inserimento:\t21:588 > CONDO-COLONNINA-SOS-10B - (x: 910, y: 10) - [show: True] in -> CONDO-IMPIANTO-SOS"}, {"message": "inserimento:\t22:588 > CONDO-GATEWAY-VOIP - (x: 955, y: 10) - [show: True] in -> CONDO-IMPIANTO-SOS"}, {"message": "inserimento:\t23:588 > CONDO-PLC-MASTER - (x: 1000, y: 10) - [show: True] in -> CONDO-IMPIANTO-SOS"}, {"message": "inserimento:\t24:588 > CONDO-RESET-ALLARMI-TUNNEL-A - (x: 1045, y: 10) - [show: True] in -> CONDO-IMPIANTO-SOS"}, {"message": "inserimento:\t25:588 > CONDO-RESET-ALLARMI-TUNNEL-B - (x: 1090, y: 10) - [show: True] in -> CONDO-IMPIANTO-SOS"}, {"message": "inserimento:\t26:588 > CONDO-RIO-SOS-1A - (x: 1135, y: 10) - [show: True] in -> CONDO-IMPIANTO-SOS"}, {"message": "inserimento:\t27:588 > CONDO-RIO-SOS-1B - (x: 1180, y: 10) - [show: True] in -> CONDO-IMPIANTO-SOS"}, {"message": "inserimento:\t28:588 > CONDO-RIO-SOS-2A - (x: 1225, y: 10) - [show: True] in -> CONDO-IMPIANTO-SOS"}, {"message": "inserimento:\t29:588 > CONDO-RIO-SOS-2B - (x: 1270, y: 10) - [show: True] in -> CONDO-IMPIANTO-SOS"}, {"message": "inserimento:\t30:588 > CONDO-RIO-SOS-3A - (x: 1315, y: 10) - [show: True] in -> CONDO-IMPIANTO-SOS"}, {"message": "inserimento:\t31:588 > CONDO-RIO-SOS-3B - (x: 1360, y: 10) - [show: True] in -> CONDO-IMPIANTO-SOS"}, {"message": "inserimento:\t32:588 > CONDO-RIO-SOS-4A - (x: 1405, y: 10) - [show: True] in -> CONDO-IMPIANTO-SOS"}, {"message": "inserimento:\t33:588 > CONDO-RIO-SOS-4B - (x: 1450, y: 10) - [show: True] in -> CONDO-IMPIANTO-SOS"}, {"message": "inserimento:\t34:588 > CONDO-RIO-SOS-5A - (x: 1495, y: 10) - [show: True] in -> CONDO-IMPIANTO-SOS"}, {"message": "inserimento:\t35:588 > CONDO-RIO-SOS-5B - (x: 1540, y: 10) - [show: True] in -> CONDO-IMPIANTO-SOS"}, {"message": "inserimento:\t36:588 > CONDO-RIO-SOS-6A - (x: 1585, y: 10) - [show: True] in -> CONDO-IMPIANTO-SOS"}, {"message": "inserimento:\t37:588 > CONDO-RIO-SOS-6B - (x: 1630, y: 10) - [show: True] in -> CONDO-IMPIANTO-SOS"}, {"message": "inserimento:\t38:588 > CONDO-RIO-SOS-7A - (x: 1675, y: 10) - [show: True] in -> CONDO-IMPIANTO-SOS"}, {"message": "inserimento:\t39:588 > CONDO-RIO-SOS-7B - (x: 1720, y: 10) - [show: True] in -> CONDO-IMPIANTO-SOS"}, {"message": "inserimento:\t40:588 > CONDO-RIO-SOS-8A - (x: 1765, y: 10) - [show: True] in -> CONDO-IMPIANTO-SOS"}, {"message": "inserimento:\t41:588 > CONDO-RIO-SOS-8B - (x: 1810, y: 10) - [show: True] in -> CONDO-IMPIANTO-SOS"}, {"message": "inserimento:\t42:588 > CONDO-RIO-SOS-9A - (x: 1855, y: 10) - [show: True] in -> CONDO-IMPIANTO-SOS"}, {"message": "inserimento:\t43:588 > CONDO-RIO-SOS-9B - (x: 1900, y: 10) - [show: True] in -> CONDO-IMPIANTO-SOS"}, {"message": "inserimento:\t44:588 > CONDO-RIO-SOS-10B - (x: 1945, y: 10) - [show: True] in -> CONDO-IMPIANTO-SOS"}, {"message": "inserimento:\t45:588 > CONDO-SWITCH-DATI-SW-CE - (x: 90, y: 35) - [show: True] in -> CONDO-IMPIANTO-SOS"}, {"message": "inserimento:\t46:588 > CONDO-SWITCH-DATI-SW-SOS1-A - (x: 135, y: 35) - [show: True] in -> CONDO-IMPIANTO-SOS"}, {"message": "inserimento:\t47:588 > CONDO-SWITCH-DATI-SW-SOS1-B - (x: 180, y: 35) - [show: True] in -> CONDO-IMPIANTO-SOS"}, {"message": "inserimento:\t48:588 > CONDO-SWITCH-DATI-SW-SOS2-A - (x: 225, y: 35) - [show: True] in -> CONDO-IMPIANTO-SOS"}, {"message": "inserimento:\t49:588 > CONDO-SWITCH-DATI-SW-SOS2-B - (x: 270, y: 35) - [show: True] in -> CONDO-IMPIANTO-SOS"}, {"message": "inserimento:\t50:588 > CONDO-SWITCH-DATI-SW-SOS3-A - (x: 315, y: 35) - [show: True] in -> CONDO-IMPIANTO-SOS"}, {"message": "inserimento:\t51:588 > CONDO-SWITCH-DATI-SW-SOS3-B - (x: 360, y: 35) - [show: True] in -> CONDO-IMPIANTO-SOS"}, {"message": "inserimento:\t52:588 > CONDO-SWITCH-DATI-SW-SOS4-A - (x: 405, y: 35) - [show: True] in -> CONDO-IMPIANTO-SOS"}, {"message": "inserimento:\t53:588 > CONDO-SWITCH-DATI-SW-SOS4-B - (x: 450, y: 35) - [show: True] in -> CONDO-IMPIANTO-SOS"}, {"message": "inserimento:\t54:588 > CONDO-SWITCH-DATI-SW-SOS5-A - (x: 495, y: 35) - [show: True] in -> CONDO-IMPIANTO-SOS"}, {"message": "inserimento:\t55:588 > CONDO-SWITCH-DATI-SW-SOS5-B - (x: 540, y: 35) - [show: True] in -> CONDO-IMPIANTO-SOS"}, {"message": "inserimento:\t56:588 > CONDO-SWITCH-DATI-SW-SOS6-A - (x: 585, y: 35) - [show: True] in -> CONDO-IMPIANTO-SOS"}, {"message": "inserimento:\t57:588 > CONDO-SWITCH-DATI-SW-SOS6-B - (x: 630, y: 35) - [show: True] in -> CONDO-IMPIANTO-SOS"}, {"message": "inserimento:\t58:588 > CONDO-SWITCH-DATI-SW-SOS7-A - (x: 675, y: 35) - [show: True] in -> CONDO-IMPIANTO-SOS"}, {"message": "inserimento:\t59:588 > CONDO-SWITCH-DATI-SW-SOS7-B - (x: 720, y: 35) - [show: True] in -> CONDO-IMPIANTO-SOS"}, {"message": "inserimento:\t60:588 > CONDO-SWITCH-DATI-SW-SOS8-A - (x: 765, y: 35) - [show: True] in -> CONDO-IMPIANTO-SOS"}, {"message": "inserimento:\t61:588 > CONDO-SWITCH-DATI-SW-SOS8-B - (x: 810, y: 35) - [show: True] in -> CONDO-IMPIANTO-SOS"}, {"message": "inserimento:\t62:588 > CONDO-SWITCH-DATI-SW-SOS9-A - (x: 855, y: 35) - [show: True] in -> CONDO-IMPIANTO-SOS"}, {"message": "inserimento:\t63:588 > CONDO-SWITCH-DATI-SW-SOS9-B - (x: 900, y: 35) - [show: True] in -> CONDO-IMPIANTO-SOS"}, {"message": "inserimento:\t64:588 > CONDO-SWITCH-DATI-SW-SOS10-A - (x: 945, y: 35) - [show: True] in -> CONDO-IMPIANTO-SOS"}, {"message": "inserimento:\t65:588 > CONDO-SWITCH-DATI-SW-SOS10-B - (x: 990, y: 35) - [show: True] in -> CONDO-IMPIANTO-SOS"}, {"message": "inserimento:\t66:588 > CONDO-SWITCH-DATI-SW-SOS11-A - (x: 1035, y: 35) - [show: True] in -> CONDO-IMPIANTO-SOS"}, {"message": "inserimento:\t67:588 > CONDO-SWITCH-DATI-SW-SOS11-B - (x: 1080, y: 35) - [show: True] in -> CONDO-IMPIANTO-SOS"}, {"message": "inserimento:\t68:588 > CONDO-VOIP-SOS-1A - (x: 1125, y: 35) - [show: True] in -> CONDO-IMPIANTO-SOS"}, {"message": "inserimento:\t69:588 > CONDO-VOIP-SOS-1B - (x: 1170, y: 35) - [show: True] in -> CONDO-IMPIANTO-SOS"}, {"message": "inserimento:\t70:588 > CONDO-VOIP-SOS-2A - (x: 1215, y: 35) - [show: True] in -> CONDO-IMPIANTO-SOS"}, {"message": "inserimento:\t71:588 > CONDO-VOIP-SOS-2B - (x: 1260, y: 35) - [show: True] in -> CONDO-IMPIANTO-SOS"}, {"message": "inserimento:\t72:588 > CONDO-VOIP-SOS-3A - (x: 1305, y: 35) - [show: True] in -> CONDO-IMPIANTO-SOS"}, {"message": "inserimento:\t73:588 > CONDO-VOIP-SOS-3B - (x: 1350, y: 35) - [show: True] in -> CONDO-IMPIANTO-SOS"}, {"message": "inserimento:\t74:588 > CONDO-VOIP-SOS-4A - (x: 1395, y: 35) - [show: True] in -> CONDO-IMPIANTO-SOS"}, {"message": "inserimento:\t75:588 > CONDO-VOIP-SOS-4B - (x: 1440, y: 35) - [show: True] in -> CONDO-IMPIANTO-SOS"}, {"message": "inserimento:\t76:588 > CONDO-VOIP-SOS-5A - (x: 1485, y: 35) - [show: True] in -> CONDO-IMPIANTO-SOS"}, {"message": "inserimento:\t77:588 > CONDO-VOIP-SOS-5B - (x: 1530, y: 35) - [show: True] in -> CONDO-IMPIANTO-SOS"}, {"message": "inserimento:\t78:588 > CONDO-VOIP-SOS-6A - (x: 1575, y: 35) - [show: True] in -> CONDO-IMPIANTO-SOS"}, {"message": "inserimento:\t79:588 > CONDO-VOIP-SOS-6B - (x: 1620, y: 35) - [show: True] in -> CONDO-IMPIANTO-SOS"}, {"message": "inserimento:\t80:588 > CONDO-VOIP-SOS-7A - (x: 1665, y: 35) - [show: True] in -> CONDO-IMPIANTO-SOS"}, {"message": "inserimento:\t81:588 > CONDO-VOIP-SOS-7B - (x: 1710, y: 35) - [show: True] in -> CONDO-IMPIANTO-SOS"}, {"message": "inserimento:\t82:588 > CONDO-VOIP-SOS-8A - (x: 1755, y: 35) - [show: True] in -> CONDO-IMPIANTO-SOS"}, {"message": "inserimento:\t83:588 > CONDO-VOIP-SOS-8B - (x: 1800, y: 35) - [show: True] in -> CONDO-IMPIANTO-SOS"}, {"message": "inserimento:\t84:588 > CONDO-VOIP-SOS-9A - (x: 1845, y: 35) - [show: True] in -> CONDO-IMPIANTO-SOS"}, {"message": "inserimento:\t85:588 > CONDO-VOIP-SOS-9B - (x: 1890, y: 35) - [show: True] in -> CONDO-IMPIANTO-SOS"}, {"message": "inserimento:\t86:588 > CONDO-VOIP-SOS-USCITA-A - (x: 1935, y: 35) - [show: True] in -> CONDO-IMPIANTO-SOS"}, {"message": "inserimento:\t87:588 > CONDO-VOIP-SOS-USCITA-B - (x: 90, y: 60) - [show: True] in -> CONDO-IMPIANTO-SOS"}, {"message": "6|17: CONDO-IMPIANTO-RILEVAMENTO-INCENDIO"}, {"message": "inserimento:\t1:588 > CONDO-ALLARME-INCENDIO - (x: 10, y: 10) - [show: True] in -> CONDO-IMPIANTO-RILEVAMENTO-INCENDIO"}, {"message": "inserimento:\t2:588 > CONDO-CENTRALINA-FIBROLASER - (x: 55, y: 10) - [show: True] in -> CONDO-IMPIANTO-RILEVAMENTO-INCENDIO"}, {"message": "inserimento:\t3:588 > CONDO-CENTRALINA-RILEVAZIONE-INCENDIO-US1 - (x: 100, y: 10) - [show: True] in -> CONDO-IMPIANTO-RILEVAMENTO-INCENDIO"}, {"message": "inserimento:\t4:588 > CONDO-CENTRALINA-RILEVAZIONE-INCENDIO-US2 - (x: 145, y: 10) - [show: True] in -> CONDO-IMPIANTO-RILEVAMENTO-INCENDIO"}, {"message": "inserimento:\t5:588 > CONDO-POMPA-JOCHEY - (x: 190, y: 10) - [show: True] in -> CONDO-IMPIANTO-RILEVAMENTO-INCENDIO"}, {"message": "inserimento:\t6:588 > CONDO-POMPA-NORMALE - (x: 235, y: 10) - [show: True] in -> CONDO-IMPIANTO-RILEVAMENTO-INCENDIO"}, {"message": "inserimento:\t7:588 > CONDO-POMPA-RISERVA - (x: 280, y: 10) - [show: True] in -> CONDO-IMPIANTO-RILEVAMENTO-INCENDIO"}, {"message": "inserimento:\t8:588 > CONDO-RILEVATORE-INCENDIO-ZONA-1-A - (x: 325, y: 10) - [show: True] in -> CONDO-IMPIANTO-RILEVAMENTO-INCENDIO"}, {"message": "inserimento:\t9:588 > CONDO-RILEVATORE-INCENDIO-ZONA-1-B - (x: 370, y: 10) - [show: True] in -> CONDO-IMPIANTO-RILEVAMENTO-INCENDIO"}, {"message": "inserimento:\t10:588 > CONDO-RILEVATORE-INCENDIO-ZONA-2-A - (x: 415, y: 10) - [show: True] in -> CONDO-IMPIANTO-RILEVAMENTO-INCENDIO"}, {"message": "inserimento:\t11:588 > CONDO-RILEVATORE-INCENDIO-ZONA-2-B - (x: 460, y: 10) - [show: True] in -> CONDO-IMPIANTO-RILEVAMENTO-INCENDIO"}, {"message": "inserimento:\t12:588 > CONDO-RILEVATORE-INCENDIO-ZONA-3-A - (x: 505, y: 10) - [show: True] in -> CONDO-IMPIANTO-RILEVAMENTO-INCENDIO"}, {"message": "inserimento:\t13:588 > CONDO-RILEVATORE-INCENDIO-ZONA-3-B - (x: 550, y: 10) - [show: True] in -> CONDO-IMPIANTO-RILEVAMENTO-INCENDIO"}, {"message": "7|17: CONDO-IMPIANTO-CANALIZZAZIONE"}, {"message": "inserimento:\t1:588 > CONDO-ABILITAZIONE-DA-RMT - (x: 10, y: 10) - [show: True] in -> CONDO-IMPIANTO-CANALIZZAZIONE"}, {"message": "inserimento:\t2:588 > CONDO-FRECCIA-CROCE-ESTERNO-MARCIA - (x: 55, y: 10) - [show: True] in -> CONDO-IMPIANTO-CANALIZZAZIONE"}, {"message": "inserimento:\t3:588 > CONDO-FRECCIA-CROCE-ESTERNO-SORPASSO - (x: 100, y: 10) - [show: True] in -> CONDO-IMPIANTO-CANALIZZAZIONE"}, {"message": "inserimento:\t4:588 > CONDO-FRECCIA-CROCE-PMV1A-MARCIA - (x: 145, y: 10) - [show: True] in -> CONDO-IMPIANTO-CANALIZZAZIONE"}, {"message": "inserimento:\t5:588 > CONDO-FRECCIA-CROCE-PMV1A-SORPASSO - (x: 190, y: 10) - [show: True] in -> CONDO-IMPIANTO-CANALIZZAZIONE"}, {"message": "inserimento:\t6:588 > CONDO-FRECCIA-CROCE-PMV1B-MARCIA - (x: 235, y: 10) - [show: True] in -> CONDO-IMPIANTO-CANALIZZAZIONE"}, {"message": "inserimento:\t7:588 > CONDO-FRECCIA-CROCE-PMV1B-SORPASSO - (x: 280, y: 10) - [show: True] in -> CONDO-IMPIANTO-CANALIZZAZIONE"}, {"message": "inserimento:\t8:588 > CONDO-FRECCIA-CROCE-PMV2A-MARCIA - (x: 325, y: 10) - [show: True] in -> CONDO-IMPIANTO-CANALIZZAZIONE"}, {"message": "inserimento:\t9:588 > CONDO-FRECCIA-CROCE-PMV2A-SORPASSO - (x: 370, y: 10) - [show: True] in -> CONDO-IMPIANTO-CANALIZZAZIONE"}, {"message": "inserimento:\t10:588 > CONDO-FRECCIA-CROCE-PMV2B-MARCIA - (x: 415, y: 10) - [show: True] in -> CONDO-IMPIANTO-CANALIZZAZIONE"}, {"message": "inserimento:\t11:588 > CONDO-FRECCIA-CROCE-PMV2B-SORPASSO - (x: 460, y: 10) - [show: True] in -> CONDO-IMPIANTO-CANALIZZAZIONE"}, {"message": "inserimento:\t12:588 > CONDO-FRECCIA-CROCE-PMV3A-MARCIA - (x: 505, y: 10) - [show: True] in -> CONDO-IMPIANTO-CANALIZZAZIONE"}, {"message": "inserimento:\t13:588 > CONDO-FRECCIA-CROCE-PMV3A-SORPASSO - (x: 550, y: 10) - [show: True] in -> CONDO-IMPIANTO-CANALIZZAZIONE"}, {"message": "inserimento:\t14:588 > CONDO-FRECCIA-CROCE-PMV3B-MARCIA - (x: 595, y: 10) - [show: True] in -> CONDO-IMPIANTO-CANALIZZAZIONE"}, {"message": "inserimento:\t15:588 > CONDO-FRECCIA-CROCE-PMV3B-SORPASSO - (x: 640, y: 10) - [show: True] in -> CONDO-IMPIANTO-CANALIZZAZIONE"}, {"message": "inserimento:\t16:588 > CONDO-FRECCIA-CROCE-PMV4A-MARCIA - (x: 685, y: 10) - [show: True] in -> CONDO-IMPIANTO-CANALIZZAZIONE"}, {"message": "inserimento:\t17:588 > CONDO-FRECCIA-CROCE-PMV4A-SORPASSO - (x: 730, y: 10) - [show: True] in -> CONDO-IMPIANTO-CANALIZZAZIONE"}, {"message": "inserimento:\t18:588 > CONDO-FRECCIA-CROCE-PMV4B-MARCIA - (x: 775, y: 10) - [show: True] in -> CONDO-IMPIANTO-CANALIZZAZIONE"}, {"message": "inserimento:\t19:588 > CONDO-FRECCIA-CROCE-PMV4B-SORPASSO - (x: 820, y: 10) - [show: True] in -> CONDO-IMPIANTO-CANALIZZAZIONE"}, {"message": "inserimento:\t20:588 > CONDO-FRECCIA-CROCE-PMV5A-MARCIA - (x: 865, y: 10) - [show: True] in -> CONDO-IMPIANTO-CANALIZZAZIONE"}, {"message": "inserimento:\t21:588 > CONDO-FRECCIA-CROCE-PMV5A-SORPASSO - (x: 910, y: 10) - [show: True] in -> CONDO-IMPIANTO-CANALIZZAZIONE"}, {"message": "inserimento:\t22:588 > CONDO-FRECCIA-CROCE-PMV5B-MARCIA - (x: 955, y: 10) - [show: True] in -> CONDO-IMPIANTO-CANALIZZAZIONE"}, {"message": "inserimento:\t23:588 > CONDO-FRECCIA-CROCE-PMV5B-SORPASSO - (x: 1000, y: 10) - [show: True] in -> CONDO-IMPIANTO-CANALIZZAZIONE"}, {"message": "inserimento:\t24:588 > CONDO-LANTERNA-SEMAFORICA-MARCIA - (x: 1045, y: 10) - [show: True] in -> CONDO-IMPIANTO-CANALIZZAZIONE"}, {"message": "inserimento:\t25:588 > CONDO-LANTERNA-SEMAFORICA-SORPASSO - (x: 1090, y: 10) - [show: True] in -> CONDO-IMPIANTO-CANALIZZAZIONE"}, {"message": "inserimento:\t26:588 > CONDO-SWITCH-DATI-SW-CE - (x: 1135, y: 10) - [show: True] in -> CONDO-IMPIANTO-CANALIZZAZIONE"}, {"message": "inserimento:\t27:588 > CONDO-SWITCH-DATI-SW-SOS1-A - (x: 1180, y: 10) - [show: True] in -> CONDO-IMPIANTO-CANALIZZAZIONE"}, {"message": "inserimento:\t28:588 > CONDO-SWITCH-DATI-SW-SOS1-B - (x: 1225, y: 10) - [show: True] in -> CONDO-IMPIANTO-CANALIZZAZIONE"}, {"message": "inserimento:\t29:588 > CONDO-SWITCH-DATI-SW-SOS3-A - (x: 1270, y: 10) - [show: True] in -> CONDO-IMPIANTO-CANALIZZAZIONE"}, {"message": "inserimento:\t30:588 > CONDO-SWITCH-DATI-SW-SOS3-B - (x: 1315, y: 10) - [show: True] in -> CONDO-IMPIANTO-CANALIZZAZIONE"}, {"message": "inserimento:\t31:588 > CONDO-SWITCH-DATI-SW-SOS6-A - (x: 1360, y: 10) - [show: True] in -> CONDO-IMPIANTO-CANALIZZAZIONE"}, {"message": "inserimento:\t32:588 > CONDO-SWITCH-DATI-SW-SOS6-B - (x: 1405, y: 10) - [show: True] in -> CONDO-IMPIANTO-CANALIZZAZIONE"}, {"message": "inserimento:\t33:588 > CONDO-SWITCH-DATI-SW-SOS8-B - (x: 1450, y: 10) - [show: True] in -> CONDO-IMPIANTO-CANALIZZAZIONE"}, {"message": "inserimento:\t34:588 > CONDO-SWITCH-DATI-SW-SOS9-A - (x: 1495, y: 10) - [show: True] in -> CONDO-IMPIANTO-CANALIZZAZIONE"}, {"message": "inserimento:\t35:588 > PMV_SS694_Gall_Condo_Km_3_870_DIR_Gallipoli_Esterno - (x: 1540, y: 10) - [show: True] in -> CONDO-IMPIANTO-CANALIZZAZIONE"}, {"message": "inserimento:\t36:588 > PMV_SS694_Gall_Condo_Km_5_018_DIR_BR - (x: 1585, y: 10) - [show: True] in -> CONDO-IMPIANTO-CANALIZZAZIONE"}, {"message": "inserimento:\t37:588 > PMV_SS694_Gall_Condo_Km_5_140_DIR_BR_Esterno - (x: 1630, y: 10) - [show: True] in -> CONDO-IMPIANTO-CANALIZZAZIONE"}, {"message": "inserimento:\t38:588 > SS694_Gall_Condo_Km_4_025_DIR_Gallipoli - (x: 1675, y: 10) - [show: True] in -> CONDO-IMPIANTO-CANALIZZAZIONE"}, {"message": "inserimento:\t39:588 > SS694_Gall_Condo_Km_4_029_DIR_BR - (x: 1720, y: 10) - [show: True] in -> CONDO-IMPIANTO-CANALIZZAZIONE"}, {"message": "inserimento:\t40:588 > SS694_Gall_Condo_Km_4_219_DIR_BR - (x: 1765, y: 10) - [show: True] in -> CONDO-IMPIANTO-CANALIZZAZIONE"}, {"message": "inserimento:\t41:588 > SS694_Gall_Condo_Km_4_320_DIR_Gallipoli - (x: 1810, y: 10) - [show: True] in -> CONDO-IMPIANTO-CANALIZZAZIONE"}, {"message": "inserimento:\t42:588 > SS694_Gall_Condo_Km_4_620_DIR_Gallipoli - (x: 1855, y: 10) - [show: True] in -> CONDO-IMPIANTO-CANALIZZAZIONE"}, {"message": "inserimento:\t43:588 > SS694_Gall_Condo_Km_4_719_DIR_BR - (x: 1900, y: 10) - [show: True] in -> CONDO-IMPIANTO-CANALIZZAZIONE"}, {"message": "inserimento:\t44:588 > SS694_Gall_Condo_Km_4_920_DIR_Gallipoli - (x: 1945, y: 10) - [show: True] in -> CONDO-IMPIANTO-CANALIZZAZIONE"}, {"message": "8|17: CONDO-IMPIANTO-VIDEOSORVEGLIANZA"}, {"message": "inserimento:\t1:588 > CONDO-PLC-MASTER - (x: 10, y: 10) - [show: True] in -> CONDO-IMPIANTO-VIDEOSORVEGLIANZA"}, {"message": "inserimento:\t2:588 > CONDO-SWITCH-DATI-SW-CE - (x: 55, y: 10) - [show: True] in -> CONDO-IMPIANTO-VIDEOSORVEGLIANZA"}, {"message": "inserimento:\t3:588 > CONDO-SWITCH-DATI-SW-SOS1-A - (x: 100, y: 10) - [show: True] in -> CONDO-IMPIANTO-VIDEOSORVEGLIANZA"}, {"message": "inserimento:\t4:588 > CONDO-SWITCH-DATI-SW-SOS1-B - (x: 145, y: 10) - [show: True] in -> CONDO-IMPIANTO-VIDEOSORVEGLIANZA"}, {"message": "inserimento:\t5:588 > CONDO-SWITCH-DATI-SW-SOS2-A - (x: 190, y: 10) - [show: True] in -> CONDO-IMPIANTO-VIDEOSORVEGLIANZA"}, {"message": "inserimento:\t6:588 > CONDO-SWITCH-DATI-SW-SOS2-B - (x: 235, y: 10) - [show: True] in -> CONDO-IMPIANTO-VIDEOSORVEGLIANZA"}, {"message": "inserimento:\t7:588 > CONDO-SWITCH-DATI-SW-SOS3-A - (x: 280, y: 10) - [show: True] in -> CONDO-IMPIANTO-VIDEOSORVEGLIANZA"}, {"message": "inserimento:\t8:588 > CONDO-SWITCH-DATI-SW-SOS3-B - (x: 325, y: 10) - [show: True] in -> CONDO-IMPIANTO-VIDEOSORVEGLIANZA"}, {"message": "inserimento:\t9:588 > CONDO-SWITCH-DATI-SW-SOS4-A - (x: 370, y: 10) - [show: True] in -> CONDO-IMPIANTO-VIDEOSORVEGLIANZA"}, {"message": "inserimento:\t10:588 > CONDO-SWITCH-DATI-SW-SOS4-B - (x: 415, y: 10) - [show: True] in -> CONDO-IMPIANTO-VIDEOSORVEGLIANZA"}, {"message": "inserimento:\t11:588 > CONDO-SWITCH-DATI-SW-SOS5-A - (x: 460, y: 10) - [show: True] in -> CONDO-IMPIANTO-VIDEOSORVEGLIANZA"}, {"message": "inserimento:\t12:588 > CONDO-SWITCH-DATI-SW-SOS5-B - (x: 505, y: 10) - [show: True] in -> CONDO-IMPIANTO-VIDEOSORVEGLIANZA"}, {"message": "inserimento:\t13:588 > CONDO-SWITCH-DATI-SW-SOS6-A - (x: 550, y: 10) - [show: True] in -> CONDO-IMPIANTO-VIDEOSORVEGLIANZA"}, {"message": "inserimento:\t14:588 > CONDO-SWITCH-DATI-SW-SOS6-B - (x: 595, y: 10) - [show: True] in -> CONDO-IMPIANTO-VIDEOSORVEGLIANZA"}, {"message": "inserimento:\t15:588 > CONDO-SWITCH-DATI-SW-SOS7-A - (x: 640, y: 10) - [show: True] in -> CONDO-IMPIANTO-VIDEOSORVEGLIANZA"}, {"message": "inserimento:\t16:588 > CONDO-SWITCH-DATI-SW-SOS7-B - (x: 685, y: 10) - [show: True] in -> CONDO-IMPIANTO-VIDEOSORVEGLIANZA"}, {"message": "inserimento:\t17:588 > CONDO-SWITCH-DATI-SW-SOS8-A - (x: 730, y: 10) - [show: True] in -> CONDO-IMPIANTO-VIDEOSORVEGLIANZA"}, {"message": "inserimento:\t18:588 > CONDO-SWITCH-DATI-SW-SOS8-B - (x: 775, y: 10) - [show: True] in -> CONDO-IMPIANTO-VIDEOSORVEGLIANZA"}, {"message": "inserimento:\t19:588 > CONDO-SWITCH-DATI-SW-SOS9-A - (x: 820, y: 10) - [show: True] in -> CONDO-IMPIANTO-VIDEOSORVEGLIANZA"}, {"message": "inserimento:\t20:588 > CONDO-SWITCH-DATI-SW-SOS9-B - (x: 865, y: 10) - [show: True] in -> CONDO-IMPIANTO-VIDEOSORVEGLIANZA"}, {"message": "inserimento:\t21:588 > CONDO-SWITCH-DATI-SW-SOS10-A - (x: 910, y: 10) - [show: True] in -> CONDO-IMPIANTO-VIDEOSORVEGLIANZA"}, {"message": "inserimento:\t22:588 > CONDO-SWITCH-DATI-SW-SOS10-B - (x: 955, y: 10) - [show: True] in -> CONDO-IMPIANTO-VIDEOSORVEGLIANZA"}, {"message": "inserimento:\t23:588 > CONDO-SWITCH-DATI-SW-SOS11-A - (x: 1000, y: 10) - [show: True] in -> CONDO-IMPIANTO-VIDEOSORVEGLIANZA"}, {"message": "inserimento:\t24:588 > CONDO-SWITCH-DATI-SW-SOS11-B - (x: 1045, y: 10) - [show: True] in -> CONDO-IMPIANTO-VIDEOSORVEGLIANZA"}, {"message": "inserimento:\t25:588 > CONDO-VIDEO-SERVER - (x: 1090, y: 10) - [show: True] in -> CONDO-IMPIANTO-VIDEOSORVEGLIANZA"}, {"message": "inserimento:\t26:588 > SS694_Gall_Condo_Km_4_010_TVCC15_B - (x: 1135, y: 10) - [show: True] in -> CONDO-IMPIANTO-VIDEOSORVEGLIANZA"}, {"message": "inserimento:\t27:588 > SS694_Gall_Condo_Km_4_044_TVCC15_A - (x: 1180, y: 10) - [show: True] in -> CONDO-IMPIANTO-VIDEOSORVEGLIANZA"}, {"message": "inserimento:\t28:588 > SS694_Gall_Condo_Km_4_095_TVCC1_B - (x: 1225, y: 10) - [show: True] in -> CONDO-IMPIANTO-VIDEOSORVEGLIANZA"}, {"message": "inserimento:\t29:588 > SS694_Gall_Condo_Km_4_124_TVCC14_A - (x: 1270, y: 10) - [show: True] in -> CONDO-IMPIANTO-VIDEOSORVEGLIANZA"}, {"message": "inserimento:\t30:588 > SS694_Gall_Condo_Km_4_170_TVCC2_B - (x: 1315, y: 10) - [show: True] in -> CONDO-IMPIANTO-VIDEOSORVEGLIANZA"}, {"message": "inserimento:\t31:588 > SS694_Gall_Condo_Km_4_194_TVCC13_A - (x: 1360, y: 10) - [show: True] in -> CONDO-IMPIANTO-VIDEOSORVEGLIANZA"}, {"message": "inserimento:\t32:588 > SS694_Gall_Condo_Km_4_245_TVCC3_B - (x: 1405, y: 10) - [show: True] in -> CONDO-IMPIANTO-VIDEOSORVEGLIANZA"}, {"message": "inserimento:\t33:588 > SS694_Gall_Condo_Km_4_274_TVCC12_A - (x: 1450, y: 10) - [show: True] in -> CONDO-IMPIANTO-VIDEOSORVEGLIANZA"}, {"message": "inserimento:\t34:588 > SS694_Gall_Condo_Km_4_320_TVCC4_B - (x: 1495, y: 10) - [show: True] in -> CONDO-IMPIANTO-VIDEOSORVEGLIANZA"}, {"message": "inserimento:\t35:588 > SS694_Gall_Condo_Km_4_344_TVCC11_A - (x: 1540, y: 10) - [show: True] in -> CONDO-IMPIANTO-VIDEOSORVEGLIANZA"}, {"message": "inserimento:\t36:588 > SS694_Gall_Condo_Km_4_395_TVCC5_B - (x: 1585, y: 10) - [show: True] in -> CONDO-IMPIANTO-VIDEOSORVEGLIANZA"}, {"message": "inserimento:\t37:588 > SS694_Gall_Condo_Km_4_424_TVCC10_A - (x: 1630, y: 10) - [show: True] in -> CONDO-IMPIANTO-VIDEOSORVEGLIANZA"}, {"message": "inserimento:\t38:588 > SS694_Gall_Condo_Km_4_470_TVCC6_B - (x: 1675, y: 10) - [show: True] in -> CONDO-IMPIANTO-VIDEOSORVEGLIANZA"}, {"message": "inserimento:\t39:588 > SS694_Gall_Condo_Km_4_494_TVCC9_A - (x: 1720, y: 10) - [show: True] in -> CONDO-IMPIANTO-VIDEOSORVEGLIANZA"}, {"message": "inserimento:\t40:588 > SS694_Gall_Condo_Km_4_545_TVCC7_B - (x: 1765, y: 10) - [show: True] in -> CONDO-IMPIANTO-VIDEOSORVEGLIANZA"}, {"message": "inserimento:\t41:588 > SS694_Gall_Condo_Km_4_574_TVCC8_A - (x: 1810, y: 10) - [show: True] in -> CONDO-IMPIANTO-VIDEOSORVEGLIANZA"}, {"message": "inserimento:\t42:588 > SS694_Gall_Condo_Km_4_584_TVCC18_AUE - (x: 1855, y: 10) - [show: True] in -> CONDO-IMPIANTO-VIDEOSORVEGLIANZA"}, {"message": "inserimento:\t43:588 > SS694_Gall_Condo_Km_4_591_TVCC17_AUE - (x: 1900, y: 10) - [show: True] in -> CONDO-IMPIANTO-VIDEOSORVEGLIANZA"}, {"message": "inserimento:\t44:588 > SS694_Gall_Condo_Km_4_597_TVCC16_AUE - (x: 1945, y: 10) - [show: True] in -> CONDO-IMPIANTO-VIDEOSORVEGLIANZA"}, {"message": "inserimento:\t45:588 > SS694_Gall_Condo_Km_4_607_TVCC8_B - (x: 90, y: 35) - [show: True] in -> CONDO-IMPIANTO-VIDEOSORVEGLIANZA"}, {"message": "inserimento:\t46:588 > SS694_Gall_Condo_Km_4_610_TVCC9_B - (x: 135, y: 35) - [show: True] in -> CONDO-IMPIANTO-VIDEOSORVEGLIANZA"}, {"message": "inserimento:\t47:588 > SS694_Gall_Condo_Km_4_624_TVCC7_A - (x: 180, y: 35) - [show: True] in -> CONDO-IMPIANTO-VIDEOSORVEGLIANZA"}, {"message": "inserimento:\t48:588 > SS694_Gall_Condo_Km_4_644_TVCC6_A - (x: 225, y: 35) - [show: True] in -> CONDO-IMPIANTO-VIDEOSORVEGLIANZA"}, {"message": "inserimento:\t49:588 > SS694_Gall_Condo_Km_4_663_TVCC16_BUE - (x: 270, y: 35) - [show: True] in -> CONDO-IMPIANTO-VIDEOSORVEGLIANZA"}, {"message": "inserimento:\t50:588 > SS694_Gall_Condo_Km_4_669_TVCC17_BUE - (x: 315, y: 35) - [show: True] in -> CONDO-IMPIANTO-VIDEOSORVEGLIANZA"}, {"message": "inserimento:\t51:588 > SS694_Gall_Condo_Km_4_675_TVCC18_BUE - (x: 360, y: 35) - [show: True] in -> CONDO-IMPIANTO-VIDEOSORVEGLIANZA"}, {"message": "inserimento:\t52:588 > SS694_Gall_Condo_Km_4_695_TVCC10_B - (x: 405, y: 35) - [show: True] in -> CONDO-IMPIANTO-VIDEOSORVEGLIANZA"}, {"message": "inserimento:\t53:588 > SS694_Gall_Condo_Km_4_724_TVCC5_A - (x: 450, y: 35) - [show: True] in -> CONDO-IMPIANTO-VIDEOSORVEGLIANZA"}, {"message": "inserimento:\t54:588 > SS694_Gall_Condo_Km_4_770_TVCC11_B - (x: 495, y: 35) - [show: True] in -> CONDO-IMPIANTO-VIDEOSORVEGLIANZA"}, {"message": "inserimento:\t55:588 > SS694_Gall_Condo_Km_4_794_TVCC4_A - (x: 540, y: 35) - [show: True] in -> CONDO-IMPIANTO-VIDEOSORVEGLIANZA"}, {"message": "inserimento:\t56:588 > SS694_Gall_Condo_Km_4_845_TVCC12_B - (x: 585, y: 35) - [show: True] in -> CONDO-IMPIANTO-VIDEOSORVEGLIANZA"}, {"message": "inserimento:\t57:588 > SS694_Gall_Condo_Km_4_874_TVCC3_A - (x: 630, y: 35) - [show: True] in -> CONDO-IMPIANTO-VIDEOSORVEGLIANZA"}, {"message": "inserimento:\t58:588 > SS694_Gall_Condo_Km_4_920_TVCC13_B - (x: 675, y: 35) - [show: True] in -> CONDO-IMPIANTO-VIDEOSORVEGLIANZA"}, {"message": "inserimento:\t59:588 > SS694_Gall_Condo_Km_4_944_TVCC2_A - (x: 720, y: 35) - [show: True] in -> CONDO-IMPIANTO-VIDEOSORVEGLIANZA"}, {"message": "inserimento:\t60:588 > SS694_Gall_Condo_Km_4_995_TVCC14_B - (x: 765, y: 35) - [show: True] in -> CONDO-IMPIANTO-VIDEOSORVEGLIANZA"}, {"message": "inserimento:\t61:588 > SS694_Gall_Condo_Km_5_009_TVCC1_A - (x: 810, y: 35) - [show: True] in -> CONDO-IMPIANTO-VIDEOSORVEGLIANZA"}, {"message": "9|17: CONDO-IMPIANTO-VENTILAZIONE"}, {"message": "inserimento:\t1:588 > CONDO-AN1-A - (x: 10, y: 10) - [show: True] in -> CONDO-IMPIANTO-VENTILAZIONE"}, {"message": "inserimento:\t2:588 > CONDO-AN1-B - (x: 55, y: 10) - [show: True] in -> CONDO-IMPIANTO-VENTILAZIONE"}, {"message": "inserimento:\t3:588 > CONDO-CO1-A - (x: 100, y: 10) - [show: True] in -> CONDO-IMPIANTO-VENTILAZIONE"}, {"message": "inserimento:\t4:588 > CONDO-CO1-B - (x: 145, y: 10) - [show: True] in -> CONDO-IMPIANTO-VENTILAZIONE"}, {"message": "inserimento:\t5:588 > CONDO-CO2-A - (x: 190, y: 10) - [show: True] in -> CONDO-IMPIANTO-VENTILAZIONE"}, {"message": "inserimento:\t6:588 > CONDO-CO2-B - (x: 235, y: 10) - [show: True] in -> CONDO-IMPIANTO-VENTILAZIONE"}, {"message": "inserimento:\t7:588 > CONDO-OP1-A - (x: 280, y: 10) - [show: True] in -> CONDO-IMPIANTO-VENTILAZIONE"}, {"message": "inserimento:\t8:588 > CONDO-OP1-B - (x: 325, y: 10) - [show: True] in -> CONDO-IMPIANTO-VENTILAZIONE"}, {"message": "inserimento:\t9:588 > CONDO-OP2-A - (x: 370, y: 10) - [show: True] in -> CONDO-IMPIANTO-VENTILAZIONE"}, {"message": "inserimento:\t10:588 > CONDO-OP2-B - (x: 415, y: 10) - [show: True] in -> CONDO-IMPIANTO-VENTILAZIONE"}, {"message": "inserimento:\t11:588 > CONDO-PARAMETRI-VENTILAZIONE - (x: 460, y: 10) - [show: True] in -> CONDO-IMPIANTO-VENTILAZIONE"}, {"message": "inserimento:\t12:588 > CONDO-PLC-MASTER - (x: 505, y: 10) - [show: True] in -> CONDO-IMPIANTO-VENTILAZIONE"}, {"message": "inserimento:\t13:588 > CONDO-QVVF-A - (x: 550, y: 10) - [show: True] in -> CONDO-IMPIANTO-VENTILAZIONE"}, {"message": "inserimento:\t14:588 > CONDO-QVVF-B - (x: 595, y: 10) - [show: True] in -> CONDO-IMPIANTO-VENTILAZIONE"}, {"message": "inserimento:\t15:588 > CONDO-VENTILATORE-V1A - (x: 640, y: 10) - [show: True] in -> CONDO-IMPIANTO-VENTILAZIONE"}, {"message": "inserimento:\t16:588 > CONDO-VENTILATORE-V1B - (x: 685, y: 10) - [show: True] in -> CONDO-IMPIANTO-VENTILAZIONE"}, {"message": "inserimento:\t17:588 > CONDO-VENTILATORE-V2A - (x: 730, y: 10) - [show: True] in -> CONDO-IMPIANTO-VENTILAZIONE"}, {"message": "inserimento:\t18:588 > CONDO-VENTILATORE-V2B - (x: 775, y: 10) - [show: True] in -> CONDO-IMPIANTO-VENTILAZIONE"}, {"message": "inserimento:\t19:588 > CONDO-VENTILATORE-V3A - (x: 820, y: 10) - [show: True] in -> CONDO-IMPIANTO-VENTILAZIONE"}, {"message": "inserimento:\t20:588 > CONDO-VENTILATORE-V3B - (x: 865, y: 10) - [show: True] in -> CONDO-IMPIANTO-VENTILAZIONE"}, {"message": "inserimento:\t21:588 > CONDO-VENTILATORE-V4A - (x: 910, y: 10) - [show: True] in -> CONDO-IMPIANTO-VENTILAZIONE"}, {"message": "inserimento:\t22:588 > CONDO-VENTILATORE-V4B - (x: 955, y: 10) - [show: True] in -> CONDO-IMPIANTO-VENTILAZIONE"}, {"message": "inserimento:\t23:588 > CONDO-VENTILATORE-V5A - (x: 1000, y: 10) - [show: True] in -> CONDO-IMPIANTO-VENTILAZIONE"}, {"message": "inserimento:\t24:588 > CONDO-VENTILATORE-V5B - (x: 1045, y: 10) - [show: True] in -> CONDO-IMPIANTO-VENTILAZIONE"}, {"message": "inserimento:\t25:588 > CONDO-VENTILATORE-V6A - (x: 1090, y: 10) - [show: True] in -> CONDO-IMPIANTO-VENTILAZIONE"}, {"message": "inserimento:\t26:588 > CONDO-VENTILATORE-V6B - (x: 1135, y: 10) - [show: True] in -> CONDO-IMPIANTO-VENTILAZIONE"}, {"message": "inserimento:\t27:588 > CONDO-VENTILATORE-V7A - (x: 1180, y: 10) - [show: True] in -> CONDO-IMPIANTO-VENTILAZIONE"}, {"message": "inserimento:\t28:588 > CONDO-VENTILATORE-V7B - (x: 1225, y: 10) - [show: True] in -> CONDO-IMPIANTO-VENTILAZIONE"}, {"message": "inserimento:\t29:588 > CONDO-VENTILAZIONE-GENERALE - (x: 1270, y: 10) - [show: True] in -> CONDO-IMPIANTO-VENTILAZIONE"}, {"message": "10|17: CONDO-IMPIANTO-USCITE-DI-SICUREZZA"}, {"message": "inserimento:\t1:588 > CONDO-CENTRALINA-ANTINTRUSIONE-US1 - (x: 10, y: 10) - [show: True] in -> CONDO-IMPIANTO-USCITE-DI-SICUREZZA"}, {"message": "inserimento:\t2:588 > CONDO-CENTRALINA-ANTINTRUSIONE-US2 - (x: 55, y: 10) - [show: True] in -> CONDO-IMPIANTO-USCITE-DI-SICUREZZA"}, {"message": "inserimento:\t3:588 > CONDO-CENTRALINA-RILEVAZIONE-INCENDIO-US1 - (x: 100, y: 10) - [show: True] in -> CONDO-IMPIANTO-USCITE-DI-SICUREZZA"}, {"message": "inserimento:\t4:588 > CONDO-CENTRALINA-RILEVAZIONE-INCENDIO-US2 - (x: 145, y: 10) - [show: True] in -> CONDO-IMPIANTO-USCITE-DI-SICUREZZA"}, {"message": "inserimento:\t5:588 > CONDO-COLONNINA-SOS-10A - (x: 190, y: 10) - [show: True] in -> CONDO-IMPIANTO-USCITE-DI-SICUREZZA"}, {"message": "inserimento:\t6:588 > CONDO-COLONNINA-SOS-10B - (x: 235, y: 10) - [show: True] in -> CONDO-IMPIANTO-USCITE-DI-SICUREZZA"}, {"message": "inserimento:\t7:588 > CONDO-PLC-MASTER - (x: 280, y: 10) - [show: True] in -> CONDO-IMPIANTO-USCITE-DI-SICUREZZA"}, {"message": "inserimento:\t8:588 > CONDO-SWITCH-DATI-SW-SOS10-A - (x: 325, y: 10) - [show: True] in -> CONDO-IMPIANTO-USCITE-DI-SICUREZZA"}, {"message": "inserimento:\t9:588 > CONDO-SWITCH-DATI-SW-SOS10-B - (x: 370, y: 10) - [show: True] in -> CONDO-IMPIANTO-USCITE-DI-SICUREZZA"}, {"message": "inserimento:\t10:588 > CONDO-VENTILATORE-US1 - (x: 415, y: 10) - [show: True] in -> CONDO-IMPIANTO-USCITE-DI-SICUREZZA"}, {"message": "inserimento:\t11:588 > CONDO-VENTILATORE-US2 - (x: 460, y: 10) - [show: True] in -> CONDO-IMPIANTO-USCITE-DI-SICUREZZA"}, {"message": "11|17: CONDO-QGBT-CE-CONDO"}, {"message": "inserimento:\t1:588 > CONDO-CE-QGBT-INT-Q1 - (x: 10, y: 10) - [show: True] in -> CONDO-QGBT-CE-CONDO"}, {"message": "inserimento:\t2:588 > CONDO-CE-QGBT-INT-Q2 - (x: 55, y: 10) - [show: True] in -> CONDO-QGBT-CE-CONDO"}, {"message": "inserimento:\t3:588 > CONDO-CE-QGBT-INT-Q3 - (x: 100, y: 10) - [show: True] in -> CONDO-QGBT-CE-CONDO"}, {"message": "inserimento:\t4:588 > CONDO-CE-QGBT-INT-Q4 - (x: 145, y: 10) - [show: True] in -> CONDO-QGBT-CE-CONDO"}, {"message": "inserimento:\t5:588 > CONDO-CE-QGBT-INT-Q5 - (x: 190, y: 10) - [show: True] in -> CONDO-QGBT-CE-CONDO"}, {"message": "inserimento:\t6:588 > CONDO-CE-QGBT-INT-Q6 - (x: 235, y: 10) - [show: True] in -> CONDO-QGBT-CE-CONDO"}, {"message": "inserimento:\t7:588 > CONDO-CE-QGBT-INT-Q7 - (x: 280, y: 10) - [show: True] in -> CONDO-QGBT-CE-CONDO"}, {"message": "inserimento:\t8:588 > CONDO-CE-QGBT-INT-Q8 - (x: 325, y: 10) - [show: True] in -> CONDO-QGBT-CE-CONDO"}, {"message": "inserimento:\t9:588 > CONDO-CE-QGBT-INT-Q9 - (x: 370, y: 10) - [show: True] in -> CONDO-QGBT-CE-CONDO"}, {"message": "inserimento:\t10:588 > CONDO-CE-QGBT-INT-Q10 - (x: 415, y: 10) - [show: True] in -> CONDO-QGBT-CE-CONDO"}, {"message": "inserimento:\t11:588 > CONDO-CE-QGBT-INT-Q11 - (x: 460, y: 10) - [show: True] in -> CONDO-QGBT-CE-CONDO"}, {"message": "inserimento:\t12:588 > CONDO-CE-QGBT-INT-Q12 - (x: 505, y: 10) - [show: True] in -> CONDO-QGBT-CE-CONDO"}, {"message": "inserimento:\t13:588 > CONDO-CE-QGBT-INT-Q13 - (x: 550, y: 10) - [show: True] in -> CONDO-QGBT-CE-CONDO"}, {"message": "inserimento:\t14:588 > CONDO-CE-QGBT-INT-Q14 - (x: 595, y: 10) - [show: True] in -> CONDO-QGBT-CE-CONDO"}, {"message": "inserimento:\t15:588 > CONDO-CE-QGBT-INT-Q15 - (x: 640, y: 10) - [show: True] in -> CONDO-QGBT-CE-CONDO"}, {"message": "inserimento:\t16:588 > CONDO-CE-QGBT-INT-Q16 - (x: 685, y: 10) - [show: True] in -> CONDO-QGBT-CE-CONDO"}, {"message": "inserimento:\t17:588 > CONDO-CE-QGBT-INT-Q17 - (x: 730, y: 10) - [show: True] in -> CONDO-QGBT-CE-CONDO"}, {"message": "inserimento:\t18:588 > CONDO-CE-QGBT-INT-Q18 - (x: 775, y: 10) - [show: True] in -> CONDO-QGBT-CE-CONDO"}, {"message": "inserimento:\t19:588 > CONDO-CE-QGBT-INT-QG1 - (x: 820, y: 10) - [show: True] in -> CONDO-QGBT-CE-CONDO"}, {"message": "inserimento:\t20:588 > CONDO-CE-QGBT-INT-QG1A - (x: 865, y: 10) - [show: True] in -> CONDO-QGBT-CE-CONDO"}, {"message": "inserimento:\t21:588 > CONDO-CE-QGBT-INT-QG2 - (x: 910, y: 10) - [show: True] in -> CONDO-QGBT-CE-CONDO"}, {"message": "inserimento:\t22:588 > CONDO-CE-QMT-INT-GENERALE - (x: 955, y: 10) - [show: True] in -> CONDO-QGBT-CE-CONDO"}, {"message": "12|17: CONDO-QVENT-CE-CONDO"}, {"message": "inserimento:\t1:588 > CONDO-CE-QVENT-INT-Q1 - (x: 10, y: 10) - [show: True] in -> CONDO-QVENT-CE-CONDO"}, {"message": "inserimento:\t2:588 > CONDO-CE-QVENT-INT-Q2 - (x: 55, y: 10) - [show: True] in -> CONDO-QVENT-CE-CONDO"}, {"message": "inserimento:\t3:588 > CONDO-CE-QVENT-INT-Q3 - (x: 100, y: 10) - [show: True] in -> CONDO-QVENT-CE-CONDO"}, {"message": "inserimento:\t4:588 > CONDO-CE-QVENT-INT-Q4 - (x: 145, y: 10) - [show: True] in -> CONDO-QVENT-CE-CONDO"}, {"message": "inserimento:\t5:588 > CONDO-CE-QVENT-INT-Q5 - (x: 190, y: 10) - [show: True] in -> CONDO-QVENT-CE-CONDO"}, {"message": "inserimento:\t6:588 > CONDO-CE-QVENT-INT-Q6 - (x: 235, y: 10) - [show: True] in -> CONDO-QVENT-CE-CONDO"}, {"message": "inserimento:\t7:588 > CONDO-CE-QVENT-INT-Q7 - (x: 280, y: 10) - [show: True] in -> CONDO-QVENT-CE-CONDO"}, {"message": "inserimento:\t8:588 > CONDO-CE-QVENT-INT-Q8 - (x: 325, y: 10) - [show: True] in -> CONDO-QVENT-CE-CONDO"}, {"message": "inserimento:\t9:588 > CONDO-CE-QVENT-INT-Q9 - (x: 370, y: 10) - [show: True] in -> CONDO-QVENT-CE-CONDO"}, {"message": "inserimento:\t10:588 > CONDO-CE-QVENT-INT-Q10 - (x: 415, y: 10) - [show: True] in -> CONDO-QVENT-CE-CONDO"}, {"message": "inserimento:\t11:588 > CONDO-CE-QVENT-INT-Q11 - (x: 460, y: 10) - [show: True] in -> CONDO-QVENT-CE-CONDO"}, {"message": "inserimento:\t12:588 > CONDO-CE-QVENT-INT-Q12 - (x: 505, y: 10) - [show: True] in -> CONDO-QVENT-CE-CONDO"}, {"message": "inserimento:\t13:588 > CONDO-CE-QVENT-INT-Q13 - (x: 550, y: 10) - [show: True] in -> CONDO-QVENT-CE-CONDO"}, {"message": "inserimento:\t14:588 > CONDO-CE-QVENT-INT-Q14 - (x: 595, y: 10) - [show: True] in -> CONDO-QVENT-CE-CONDO"}, {"message": "inserimento:\t15:588 > CONDO-CE-QVENT-QG - (x: 640, y: 10) - [show: True] in -> CONDO-QVENT-CE-CONDO"}, {"message": "13|17: CONDO-QIS-CE-CONDO"}, {"message": "inserimento:\t1:588 > CONDO-CE-QIS-INT-Q1 - (x: 10, y: 10) - [show: True] in -> CONDO-QIS-CE-CONDO"}, {"message": "inserimento:\t2:588 > CONDO-CE-QIS-INT-Q2 - (x: 55, y: 10) - [show: True] in -> CONDO-QIS-CE-CONDO"}, {"message": "inserimento:\t3:588 > CONDO-CE-QIS-INT-Q3 - (x: 100, y: 10) - [show: True] in -> CONDO-QIS-CE-CONDO"}, {"message": "inserimento:\t4:588 > CONDO-CE-QIS-INT-Q4 - (x: 145, y: 10) - [show: True] in -> CONDO-QIS-CE-CONDO"}, {"message": "inserimento:\t5:588 > CONDO-CE-QIS-INT-Q5 - (x: 190, y: 10) - [show: True] in -> CONDO-QIS-CE-CONDO"}, {"message": "inserimento:\t6:588 > CONDO-CE-QIS-INT-Q6 - (x: 235, y: 10) - [show: True] in -> CONDO-QIS-CE-CONDO"}, {"message": "inserimento:\t7:588 > CONDO-CE-QIS-INT-Q7 - (x: 280, y: 10) - [show: True] in -> CONDO-QIS-CE-CONDO"}, {"message": "inserimento:\t8:588 > CONDO-CE-QIS-INT-Q8 - (x: 325, y: 10) - [show: True] in -> CONDO-QIS-CE-CONDO"}, {"message": "inserimento:\t9:588 > CONDO-CE-QIS-INT-Q9 - (x: 370, y: 10) - [show: True] in -> CONDO-QIS-CE-CONDO"}, {"message": "inserimento:\t10:588 > CONDO-CE-QIS-INT-Q10 - (x: 415, y: 10) - [show: True] in -> CONDO-QIS-CE-CONDO"}, {"message": "inserimento:\t11:588 > CONDO-CE-QIS-INT-Q11 - (x: 460, y: 10) - [show: True] in -> CONDO-QIS-CE-CONDO"}, {"message": "inserimento:\t12:588 > CONDO-CE-QIS-INT-Q12 - (x: 505, y: 10) - [show: True] in -> CONDO-QIS-CE-CONDO"}, {"message": "inserimento:\t13:588 > CONDO-CE-QIS-INT-Q13 - (x: 550, y: 10) - [show: True] in -> CONDO-QIS-CE-CONDO"}, {"message": "inserimento:\t14:588 > CONDO-CE-QIS-INT-Q16 - (x: 595, y: 10) - [show: True] in -> CONDO-QIS-CE-CONDO"}, {"message": "inserimento:\t15:588 > CONDO-CE-QIS-INT-Q17 - (x: 640, y: 10) - [show: True] in -> CONDO-QIS-CE-CONDO"}, {"message": "inserimento:\t16:588 > CONDO-CE-QIS-INT-Q18 - (x: 685, y: 10) - [show: True] in -> CONDO-QIS-CE-CONDO"}, {"message": "inserimento:\t17:588 > CONDO-CE-QIS-INT-Q19 - (x: 730, y: 10) - [show: True] in -> CONDO-QIS-CE-CONDO"}, {"message": "inserimento:\t18:588 > CONDO-CE-QIS-INT-Q20 - (x: 775, y: 10) - [show: True] in -> CONDO-QIS-CE-CONDO"}, {"message": "inserimento:\t19:588 > CONDO-CE-QIS-INT-Q21 - (x: 820, y: 10) - [show: True] in -> CONDO-QIS-CE-CONDO"}, {"message": "inserimento:\t20:588 > CONDO-CE-QIS-INT-Q22 - (x: 865, y: 10) - [show: True] in -> CONDO-QIS-CE-CONDO"}, {"message": "inserimento:\t21:588 > CONDO-CE-QIS-INT-Q23 - (x: 910, y: 10) - [show: True] in -> CONDO-QIS-CE-CONDO"}, {"message": "inserimento:\t22:588 > CONDO-CE-QIS-INT-Q24 - (x: 955, y: 10) - [show: True] in -> CONDO-QIS-CE-CONDO"}, {"message": "inserimento:\t23:588 > CONDO-CE-QIS-INT-Q25 - (x: 1000, y: 10) - [show: True] in -> CONDO-QIS-CE-CONDO"}, {"message": "inserimento:\t24:588 > CONDO-CE-QIS-INT-Q26 - (x: 1045, y: 10) - [show: True] in -> CONDO-QIS-CE-CONDO"}, {"message": "inserimento:\t25:588 > CONDO-CE-QIS-INT-Q27 - (x: 1090, y: 10) - [show: True] in -> CONDO-QIS-CE-CONDO"}, {"message": "inserimento:\t26:588 > CONDO-CE-QIS-INT-Q28 - (x: 1135, y: 10) - [show: True] in -> CONDO-QIS-CE-CONDO"}, {"message": "inserimento:\t27:588 > CONDO-CE-QIS-INT-Q29 - (x: 1180, y: 10) - [show: True] in -> CONDO-QIS-CE-CONDO"}, {"message": "inserimento:\t28:588 > CONDO-CE-QIS-INT-Q30 - (x: 1225, y: 10) - [show: True] in -> CONDO-QIS-CE-CONDO"}, {"message": "inserimento:\t29:588 > CONDO-CE-QIS-INT-Q31 - (x: 1270, y: 10) - [show: True] in -> CONDO-QIS-CE-CONDO"}, {"message": "inserimento:\t30:588 > CONDO-CE-QIS-INT-Q32 - (x: 1315, y: 10) - [show: True] in -> CONDO-QIS-CE-CONDO"}, {"message": "inserimento:\t31:588 > CONDO-CE-QIS-INT-Q33 - (x: 1360, y: 10) - [show: True] in -> CONDO-QIS-CE-CONDO"}, {"message": "inserimento:\t32:588 > CONDO-CE-QIS-INT-Q34 - (x: 1405, y: 10) - [show: True] in -> CONDO-QIS-CE-CONDO"}, {"message": "inserimento:\t33:588 > CONDO-CE-QIS-INT-Q35 - (x: 1450, y: 10) - [show: True] in -> CONDO-QIS-CE-CONDO"}, {"message": "inserimento:\t34:588 > CONDO-CE-QIS-INT-Q36 - (x: 1495, y: 10) - [show: True] in -> CONDO-QIS-CE-CONDO"}, {"message": "inserimento:\t35:588 > CONDO-CE-QIS-INT-Q37 - (x: 1540, y: 10) - [show: True] in -> CONDO-QIS-CE-CONDO"}, {"message": "inserimento:\t36:588 > CONDO-CE-QIS-INT-Q38 - (x: 1585, y: 10) - [show: True] in -> CONDO-QIS-CE-CONDO"}, {"message": "inserimento:\t37:588 > CONDO-CE-QIS-INT-Q39 - (x: 1630, y: 10) - [show: True] in -> CONDO-QIS-CE-CONDO"}, {"message": "inserimento:\t38:588 > CONDO-CE-QIS-INT-Q40 - (x: 1675, y: 10) - [show: True] in -> CONDO-QIS-CE-CONDO"}, {"message": "inserimento:\t39:588 > CONDO-CE-QIS-INT-Q41 - (x: 1720, y: 10) - [show: True] in -> CONDO-QIS-CE-CONDO"}, {"message": "inserimento:\t40:588 > CONDO-CE-QIS-INT-QG - (x: 1765, y: 10) - [show: True] in -> CONDO-QIS-CE-CONDO"}, {"message": "14|17: CONDO-QUS1-CE-CONDO"}, {"message": "inserimento:\t1:588 > CONDO-CE-QUS1-INT-Q1 - (x: 10, y: 10) - [show: True] in -> CONDO-QUS1-CE-CONDO"}, {"message": "inserimento:\t2:588 > CONDO-CE-QUS1-INT-Q2 - (x: 55, y: 10) - [show: True] in -> CONDO-QUS1-CE-CONDO"}, {"message": "inserimento:\t3:588 > CONDO-CE-QUS1-INT-Q3 - (x: 100, y: 10) - [show: True] in -> CONDO-QUS1-CE-CONDO"}, {"message": "inserimento:\t4:588 > CONDO-CE-QUS1-INT-Q4 - (x: 145, y: 10) - [show: True] in -> CONDO-QUS1-CE-CONDO"}, {"message": "inserimento:\t5:588 > CONDO-CE-QUS1-INT-Q5 - (x: 190, y: 10) - [show: True] in -> CONDO-QUS1-CE-CONDO"}, {"message": "inserimento:\t6:588 > CONDO-CE-QUS1-INT-Q6 - (x: 235, y: 10) - [show: True] in -> CONDO-QUS1-CE-CONDO"}, {"message": "inserimento:\t7:588 > CONDO-CE-QUS1-INT-Q7 - (x: 280, y: 10) - [show: True] in -> CONDO-QUS1-CE-CONDO"}, {"message": "inserimento:\t8:588 > CONDO-CE-QUS1-INT-Q8 - (x: 325, y: 10) - [show: True] in -> CONDO-QUS1-CE-CONDO"}, {"message": "inserimento:\t9:588 > CONDO-CE-QUS1-INT-QG - (x: 370, y: 10) - [show: True] in -> CONDO-QUS1-CE-CONDO"}, {"message": "15|17: CONDO-QUS2-CE-CONDO"}, {"message": "inserimento:\t1:588 > CONDO-CE-QUS2-INT-Q1 - (x: 10, y: 10) - [show: True] in -> CONDO-QUS2-CE-CONDO"}, {"message": "inserimento:\t2:588 > CONDO-CE-QUS2-INT-Q2 - (x: 55, y: 10) - [show: True] in -> CONDO-QUS2-CE-CONDO"}, {"message": "inserimento:\t3:588 > CONDO-CE-QUS2-INT-Q3 - (x: 100, y: 10) - [show: True] in -> CONDO-QUS2-CE-CONDO"}, {"message": "inserimento:\t4:588 > CONDO-CE-QUS2-INT-Q4 - (x: 145, y: 10) - [show: True] in -> CONDO-QUS2-CE-CONDO"}, {"message": "inserimento:\t5:588 > CONDO-CE-QUS2-INT-Q5 - (x: 190, y: 10) - [show: True] in -> CONDO-QUS2-CE-CONDO"}, {"message": "inserimento:\t6:588 > CONDO-CE-QUS2-INT-Q6 - (x: 235, y: 10) - [show: True] in -> CONDO-QUS2-CE-CONDO"}, {"message": "inserimento:\t7:588 > CONDO-CE-QUS2-INT-Q7 - (x: 280, y: 10) - [show: True] in -> CONDO-QUS2-CE-CONDO"}, {"message": "inserimento:\t8:588 > CONDO-CE-QUS2-INT-Q8 - (x: 325, y: 10) - [show: True] in -> CONDO-QUS2-CE-CONDO"}, {"message": "inserimento:\t9:588 > CONDO-CE-QUS2-INT-QG - (x: 370, y: 10) - [show: True] in -> CONDO-QUS2-CE-CONDO"}, {"message": "16|17: CONDO-QRINF-CE-CONDO"}, {"message": "inserimento:\t1:588 > CONDO-CE-QRINF-INT-Q1 - (x: 10, y: 10) - [show: True] in -> CONDO-QRINF-CE-CONDO"}, {"message": "inserimento:\t2:588 > CONDO-CE-QRINF-INT-Q2 - (x: 55, y: 10) - [show: True] in -> CONDO-QRINF-CE-CONDO"}, {"message": "inserimento:\t3:588 > CONDO-CE-QRINF-INT-Q3 - (x: 100, y: 10) - [show: True] in -> CONDO-QRINF-CE-CONDO"}, {"message": "inserimento:\t4:588 > CONDO-CE-QRINF-INT-Q4 - (x: 145, y: 10) - [show: True] in -> CONDO-QRINF-CE-CONDO"}, {"message": "inserimento:\t5:588 > CONDO-CE-QRINF-INT-Q5 - (x: 190, y: 10) - [show: True] in -> CONDO-QRINF-CE-CONDO"}, {"message": "inserimento:\t6:588 > CONDO-CE-QRINF-INT-Q6 - (x: 235, y: 10) - [show: True] in -> CONDO-QRINF-CE-CONDO"}, {"message": "inserimento:\t7:588 > CONDO-CE-QRINF-INT-Q7 - (x: 280, y: 10) - [show: True] in -> CONDO-QRINF-CE-CONDO"}, {"message": "inserimento:\t8:588 > CONDO-CE-QRINF-INT-Q8 - (x: 325, y: 10) - [show: True] in -> CONDO-QRINF-CE-CONDO"}, {"message": "inserimento:\t9:588 > CONDO-CE-QRINF-INT-Q10 - (x: 370, y: 10) - [show: True] in -> CONDO-QRINF-CE-CONDO"}, {"message": "inserimento:\t10:588 > CONDO-CE-QRINF-INT-Q11 - (x: 415, y: 10) - [show: True] in -> CONDO-QRINF-CE-CONDO"}, {"message": "inserimento:\t11:588 > CONDO-CE-QRINF-INT-Q12 - (x: 460, y: 10) - [show: True] in -> CONDO-QRINF-CE-CONDO"}, {"message": "inserimento:\t12:588 > CONDO-CE-QRINF-INT-QG1 - (x: 505, y: 10) - [show: True] in -> CONDO-QRINF-CE-CONDO"}, {"message": "inserimento:\t13:588 > CONDO-CE-QRINF-INT-QG2 - (x: 550, y: 10) - [show: True] in -> CONDO-QRINF-CE-CONDO"}, {"message": "17|17: CONDO-ILLUMINAZIONE-CENTRALINA"}, {"message": "Finito"}, {"message": "Tempo elaborazione: 0:53 minuti"}], "progress": 100.5, "task": "Posizionamento dispositivi negli impianti (OLD).py", "timestamp": "2025-10-10_13.00.57"}, "QqrOnmGXPm9LgIkkAAAN": {"clientName": "172.16.213.39", "data": {"collection": "", "database": "Quality", "files": ["RA15 device list per posizionamento automatico.xlsx"], "galleria": "", "script": "Posizionamento dispositivi negli impianti", "subCollection": "", "userId": "QqrOnmGXPm9LgIkkAAAN"}, "id": "QqrOnmGXPm9LgIkkAAAN", "links": [], "message": [{"message": "RA15 device list per posizionamento automatico.xlsx"}, {"message": "Cercando..."}, {"message": "An error occurred: 'NoneType' object has no attribute 'columns':"}, {"message": "Tempo elaborazione: 0:00 minuti"}], "progress": 0, "task": "Posizionamento dispositivi negli impianti (OLD).py", "timestamp": "2025-10-13_11.34.10"}, "Wa0fd_ZN9fpx2DOUAAAD": {"clientName": "172.16.215.68", "data": {"collection": "", "database": "", "files": ["TermineRmt20211206 (1).xlsx"], "galleria": "", "script": "Unisci file excel", "subCollection": "", "userId": "Wa0fd_ZN9fpx2DOUAAAD"}, "id": "Wa0fd_ZN9fpx2DOUAAAD", "links": [{"link": "C:\\Users\\Utente\\Documents\\AI_Helper\\backend\\downloads\\Unisci file excel\\10-10-2025\\2025-10-101LCSBY-TermineRmt20211206 (1).xlsx", "linkName": "2025-10-101LCSBY-TermineRmt20211206 (1).xlsx"}], "message": [{"message": [{"collection": "", "database": "", "files": ["TermineRmt20211206 (1).xlsx"], "galleria": "", "script": "Unisci file excel", "subCollection": "", "userId": "Wa0fd_ZN9fpx2DOUAAAD"}, 33.8]}, {"message": "\nAttendere...elaborazione di 1 file..."}, {"message": "\nSalvataggio in corso...\n"}, {"message": ""}, {"message": "Tempo elaborazione: 1.69 secondi - 0.01 minuti"}], "progress": 0, "task": "Unisci file excel.py", "timestamp": "2025-10-10_10.34.04"}, "pIEbnOXCueZdf557AAAJ": {"clientName": "172.16.215.68", "data": {"collection": "", "database": "Produzione", "files": null, "galleria": "termine", "script": "Scarico galleria da DragonFly", "subCollection": "", "userId": "pIEbnOXCueZdf557AAAJ"}, "id": "pIEbnOXCueZdf557AAAJ", "links": [{"link": "C:\\Users\\Utente\\Documents\\AI_Helper\\backend\\downloads\\Scarichi Dragonfly\\10-10-2025\\Scarico_DragonFly_Produzione_termine_2025-10-10_10.57.53.xlsx", "linkName": "Scarico_DragonFly_Produzione_termine_2025-10-10_10.57.53.xlsx"}], "message": [{"message": "...cercando 'termine'...nel db [Produzione]"}, {"message": "...trovato: 'TERMINE-OPERA'"}, {"message": "\nEstrazione da db..."}, {"message": "\tEstratti 6 elementi | (CPU) core utilizzato: 3/11\tProcessi rimasti da elaborare: (11)"}, {"message": "\tEstratti 23 elementi | (CPU) core utilizzato: 10/11\tProcessi rimasti da elaborare: (10)"}, {"message": "\tEstratti 32 elementi | (CPU) core utilizzato: 8/11\tProcessi rimasti da elaborare: (9)"}, {"message": "\tEstratti 34 elementi | (CPU) core utilizzato: 11/11\tProcessi rimasti da elaborare: (8)"}, {"message": "\tEstratti 42 elementi | (CPU) core utilizzato: 0/11\tProcessi rimasti da elaborare: (7)"}, {"message": "\tEstratti 41 elementi | (CPU) core utilizzato: 1/11\tProcessi rimasti da elaborare: (6)"}, {"message": "\tEstratti 50 elementi | (CPU) core utilizzato: 4/11\tProcessi rimasti da elaborare: (5)"}, {"message": "\tEstratti 51 elementi | (CPU) core utilizzato: 6/11\tProcessi rimasti da elaborare: (4)"}, {"message": "\tEstratti 67 elementi | (CPU) core utilizzato: 5/11\tProcessi rimasti da elaborare: (3)"}, {"message": "\tEstratti 77 elementi | (CPU) core utilizzato: 7/11\tProcessi rimasti da elaborare: (2)"}, {"message": "\tEstratti 92 elementi | (CPU) core utilizzato: 2/11\tProcessi rimasti da elaborare: (1)"}, {"message": "\tEstratti 151 elementi | (CPU) core utilizzato: 9/11\tProcessi rimasti da elaborare: (0)"}, {"message": "Salvataggio copia degli script in corso..."}, {"message": "Salvataggio in corso di 4175 elementi su dataframe..."}, {"message": "Salvataggio: True"}, {"message": "Salvataggio dei dati mancanti"}, {"message": "Tempo elaborazione: 182.83 secondi - 3.02 minuti"}], "progress": 100.5, "task": "Scarico automatico da DragonFly.py", "timestamp": "2025-10-10_10.57.50"}, "wybIFjnMPfUf9MLQAAAF": {"clientName": "172.16.215.68", "data": {"collection": "", "database": "", "files": ["TermineRmt20211206 (1).xlsx"], "galleria": "", "script": "Unisci file excel", "subCollection": "", "userId": "wybIFjnMPfUf9MLQAAAF"}, "id": "wybIFjnMPfUf9MLQAAAF", "links": [{"link": "C:\\Users\\Utente\\Documents\\AI_Helper\\backend\\downloads\\Unisci file excel\\10-10-2025\\2025-10-100WFF22-TermineRmt20211206 (1).xlsx", "linkName": "2025-10-100WFF22-TermineRmt20211206 (1).xlsx"}], "message": [{"message": [{"collection": "", "database": "", "files": ["TermineRmt20211206 (1).xlsx"], "galleria": "", "script": "Unisci file excel", "subCollection": "", "userId": "wybIFjnMPfUf9MLQAAAF"}, 33.9]}, {"message": "\nAttendere...elaborazione di 1 file..."}, {"message": "\nSalvataggio in corso...\n"}, {"message": ""}, {"message": "Tempo elaborazione: 1.50 secondi - 0.01 minuti"}], "progress": 0, "task": "Unisci file excel.py", "timestamp": "2025-10-10_10.41.53"}}